{
"autoplayBgm":true,"autoplayBgs":false,"battleback1Name":"","battleback2Name":"","bgm":{"name":"287_night_wind","pan":0,"pitch":100,"volume":90},"bgs":{"name":"","pan":0,"pitch":100,"volume":90},"disableDashing":false,"displayName":"","encounterList":[],"encounterStep":30,"height":13,"note":"","parallaxLoopX":true,"parallaxLoopY":false,"parallaxName":"Space","parallaxShow":true,"parallaxSx":-3,"parallaxSy":0,"scrollType":0,"specifyBattleback":false,"tilesetId":1,"width":17,
"data":[0,0,0,0,0,0,0,0,0,0,0,0,0,0,0,0,0,0,0,0,0,0,0,0,0,0,0,0,0,0,0,0,0,0,0,0,0,0,0,0,0,0,0,0,0,0,0,0,0,0,0,0,0,0,0,0,0,0,0,0,0,0,0,0,0,0,0,0,0,0,0,0,0,0,0,0,0,0,0,0,0,0,0,0,0,0,0,0,0,0,0,0,0,0,0,0,0,0,0,0,0,0,0,0,0,0,0,0,0,0,0,0,0,0,0,0,0,0,0,0,0,0,0,0,0,0,0,0,0,0,0,0,0,0,0,0,0,0,0,0,0,0,0,0,0,0,0,0,0,0,0,0,0,0,0,0,0,0,0,0,0,0,0,0,0,0,0,0,0,0,0,0,0,0,0,0,0,0,0,0,0,0,0,0,0,0,0,0,0,0,0,0,0,0,0,0,0,0,0,0,0,0,0,0,0,0,0,0,0,0,0,0,0,0,0,0,0,0,0,0,0,0,0,0,0,0,0,0,0,0,0,0,0,0,0,0,0,0,0,0,0,0,0,0,0,0,0,0,0,0,0,0,0,0,0,0,0,0,0,0,0,0,0,0,0,0,0,0,0,0,0,0,0,0,0,0,0,0,0,0,0,0,0,0,0,0,0,0,0,0,0,0,0,0,0,0,0,0,0,0,0,0,0,0,0,0,0,0,0,0,0,0,0,0,0,0,0,0,0,0,0,0,0,0,0,0,0,0,0,0,0,0,0,0,0,0,0,0,0,0,0,0,0,0,0,0,0,0,0,0,0,0,0,0,0,0,0,0,0,0,0,0,0,0,0,0,0,0,0,0,0,0,0,0,0,0,0,0,0,0,0,0,0,0,0,0,0,0,0,0,0,0,0,0,0,0,0,0,0,0,0,0,0,0,0,0,0,0,0,0,0,0,0,0,0,0,0,0,0,0,0,0,0,0,0,0,0,0,0,0,0,0,0,0,0,0,0,0,0,0,0,0,0,0,0,0,0,0,0,0,0,0,0,0,0,0,0,0,0,0,0,0,0,0,0,0,0,0,0,0,0,0,0,0,0,0,0,0,0,0,0,0,0,0,0,0,0,0,0,0,0,0,0,0,0,0,0,0,0,0,0,0,0,0,0,0,0,0,0,0,0,0,0,0,0,0,0,0,0,0,0,0,0,0,0,0,0,0,0,0,0,0,0,0,0,0,0,0,0,0,0,0,0,0,0,0,0,0,0,0,0,0,0,0,0,0,0,0,0,0,0,0,0,0,0,0,0,0,0,0,0,0,0,0,0,0,0,0,0,0,0,0,0,0,0,0,0,0,0,0,0,0,0,0,0,0,0,0,0,0,0,0,0,0,0,0,0,0,0,0,0,0,0,0,0,0,0,0,0,0,0,0,0,0,0,0,0,0,0,0,0,0,0,0,0,0,0,0,0,0,0,0,0,0,0,0,0,0,0,0,0,0,0,0,0,0,0,0,0,0,0,0,0,0,0,0,0,0,0,0,0,0,0,0,0,0,0,0,0,0,0,0,0,0,0,0,0,0,0,0,0,0,0,0,0,0,0,0,0,0,0,0,0,0,0,0,0,0,0,0,0,0,0,0,0,0,0,0,0,0,0,0,0,0,0,0,0,0,0,0,0,0,0,0,0,0,0,0,0,0,0,0,0,0,0,0,0,0,0,0,0,0,0,0,0,0,0,0,0,0,0,0,0,0,0,0,0,0,0,0,0,0,0,0,0,0,0,0,0,0,0,0,0,0,0,0,0,0,0,0,0,0,0,0,0,0,0,0,0,0,0,0,0,0,0,0,0,0,0,0,0,0,0,0,0,0,0,0,0,0,0,0,0,0,0,0,0,0,0,0,0,0,0,0,0,0,0,0,0,0,0,0,0,0,0,0,0,0,0,0,0,0,0,0,0,0,0,0,0,0,0,0,0,0,0,0,0,0,0,0,0,0,0,0,0,0,0,0,0,0,0,0,0,0,0,0,0,0,0,0,0,0,0,0,0,0,0,0,0,0,0,0,0,0,0,0,0,0,0,0,0,0,0,0,0,0,0,0,0,0,0,0,0,0,0,0,0,0,0,0,0,0,0,0,0,0,0,0,0,0,0,0,0,0,0,0,0,0,0,0,0,0,0,0,0,0,0,0,0,0,0,0,0,0,0,0,0,0,0,0,0,0,0,0,0,0,0,0,0,0,0,0,0,0,0,0,0,0,0,0,0,0,0,0,0,0,0,0,0,0,0,0,0,0,0,0,0,0,0,0,0,0,0,0,0,0,0,0,0,0,0,0,0,0,0,0,0,0,0,0,0,0,0,0,0,0,0,0,0,0,0,0,0,0,0,0,0,0,0,0,0,0,0,0,0,0,0,0,0,0,0,0,0,0,0,0,0,0,0,0,0,0,0,0,0,0,0,0,0,0,0,0,0,0,0,0,0,0,0,0,0,0,0,0,0,0,0,0,0,0,0,0,0,0,0,0,0,0,0,0,0,0,0,0,0,0,0,0,0,0,0,0,0,0,0,0,0,0,0,0,0,0,0,0,0,0,0,0,0,0,0,0,0,0,0,0,0,0,0,0,0,0,0,0,0,0,0,0,0,0,0,0,0,0,0,0,0,0,0,0,0,0,0,0,0,0,0,0,0,0,0,0,0,0,0,0,0,0,0,0,0,0,0,0,0,0,0,0,0,0,0,0,0,0,0,0,0,0,0,0,0,0,0,0,0,0,0,0,0,0,0,0,0,0,0,0,0,0,0,0,0,0,0,0,0,0,0,0,0,0,0,0,0,0,0,0,0,0,0,0,0,0,0,0,0,0,0,0,0,0,0,0,0,0,0,0,0,0,0,0,0,0,0,0,0,0,0,0,0,0,0,0,0,0,0,0,0,0,0,0,0,0,0,0,0,0,0,0,0,0,0,0,0,0,0,0,0,0,0,0,0,0,0,0,0,0,0,0,0,0,0,0,0,0,0,0],
"events":[
null,
{"id":1,"name":"結局順序","note":"","pages":[{"conditions":{"actorId":1,"actorValid":false,"itemId":1,"itemValid":false,"selfSwitchCh":"A","selfSwitchValid":false,"switch1Id":73,"switch1Valid":true,"switch2Id":1,"switch2Valid":false,"variableId":53,"variableValid":true,"variableValue":0},"directionFix":false,"image":{"characterIndex":0,"characterName":"","direction":2,"pattern":0,"tileId":0},"list":[{"code":241,"indent":0,"parameters":[{"name":"287_night_wind","volume":90,"pitch":100,"pan":0}]},{"code":281,"indent":0,"parameters":[1]},{"code":122,"indent":0,"parameters":[53,53,0,0,0]},{"code":357,"indent":0,"parameters":["VisuMZ_1_EventsMoveCore","EventLabelVisible","Event Label: Visible",{"Visibility:str":"Hidden"}]},{"code":657,"indent":0,"parameters":["Visibility = Hidden"]},{"code":222,"indent":0,"parameters":[]},{"code":122,"indent":0,"parameters":[11,11,0,0,0]},{"code":122,"indent":0,"parameters":[12,12,0,0,-40]},{"code":117,"indent":0,"parameters":[13]},{"code":250,"indent":0,"parameters":[{"name":"Magic6","volume":90,"pitch":100,"pan":0}]},{"code":231,"indent":0,"parameters":[99,"Serpent's Hand_LOGO",1,1,11,12,100,100,0,0]},{"code":234,"indent":0,"parameters":[99,[0,0,0,255],1,false]},{"code":232,"indent":0,"parameters":[99,0,1,1,11,12,100,100,255,0,20,true,0]},{"code":230,"indent":0,"parameters":[60]},{"code":101,"indent":0,"parameters":["",0,1,1,""]},{"code":401,"indent":0,"parameters":["<center>自由與秩序長久以來不斷相爭，有時是秩序勝利、有時是自由佔上風，"]},{"code":401,"indent":0,"parameters":["而這一次，蛇之手最終獲得了勝利，帷幕被撕裂，"]},{"code":401,"indent":0,"parameters":["這群自由鬥士們達成了他們長久以來的目標。"]},{"code":108,"indent":0,"parameters":["※計算和平與否"]},{"code":111,"indent":0,"parameters":[1,36,0,25,1]},{"code":121,"indent":1,"parameters":[86,86,1]},{"code":0,"indent":1,"parameters":[]},{"code":411,"indent":0,"parameters":[]},{"code":121,"indent":1,"parameters":[86,86,0]},{"code":0,"indent":1,"parameters":[]},{"code":412,"indent":0,"parameters":[]},{"code":111,"indent":0,"parameters":[0,83,0]},{"code":121,"indent":1,"parameters":[86,86,0]},{"code":0,"indent":1,"parameters":[]},{"code":412,"indent":0,"parameters":[]},{"code":108,"indent":0,"parameters":["※結局1"]},{"code":408,"indent":0,"parameters":["世界的狀況"]},{"code":122,"indent":0,"parameters":[53,53,0,0,1]},{"code":122,"indent":0,"parameters":[11,11,0,0,0]},{"code":122,"indent":0,"parameters":[12,12,0,0,0]},{"code":117,"indent":0,"parameters":[13]},{"code":250,"indent":0,"parameters":[{"name":"Book1","volume":90,"pitch":100,"pan":0}]},{"code":231,"indent":0,"parameters":[99,"ending/ENDIND1",1,1,11,12,100,100,0,0]},{"code":234,"indent":0,"parameters":[99,[0,0,0,255],1,false]},{"code":232,"indent":0,"parameters":[99,0,1,1,11,12,100,100,255,0,20,true,0]},{"code":111,"indent":0,"parameters":[0,86,0]},{"code":101,"indent":1,"parameters":["",0,1,2,""]},{"code":401,"indent":1,"parameters":["<center>帷幕被揭露後，世界陷入了一片混亂，"]},{"code":401,"indent":1,"parameters":["儘管GOC在歐提克之戰受到了毀滅性的打擊，並且很快就解體了，"]},{"code":401,"indent":1,"parameters":["但過往帷幕外的人們見到了蛇之手為撕裂帷幕所做出的事情，並沒有如蛇之手所想的接受他們。"]},{"code":250,"indent":1,"parameters":[{"name":"Book1","volume":90,"pitch":100,"pan":0}]},{"code":101,"indent":1,"parameters":["",0,1,2,""]},{"code":401,"indent":1,"parameters":["<center>被視為怪物的人們在帷幕被撕裂後仍舊被視作怪物，"]},{"code":401,"indent":1,"parameters":["世界如基金會與GOC他們所預料的相同，在揭露帷幕後陷入了前所未有的大混亂，"]},{"code":401,"indent":1,"parameters":["一個又一個新的反蛇之手組織誕生，並將異常人類視作人類的公敵，蛇之手也只能以武力回應。"]},{"code":250,"indent":1,"parameters":[{"name":"Book1","volume":90,"pitch":100,"pan":0}]},{"code":101,"indent":1,"parameters":["",0,1,2,""]},{"code":401,"indent":1,"parameters":["<center>最終佔上風的蛇之手們終究不得不打造一個優待於超人類，"]},{"code":401,"indent":1,"parameters":["迫害基準人類，遠比戰前的世界更加糟糕的惡劣世界。"]},{"code":0,"indent":1,"parameters":[]},{"code":411,"indent":0,"parameters":[]},{"code":101,"indent":1,"parameters":["",0,1,2,""]},{"code":401,"indent":1,"parameters":["<center>帷幕被揭露後，世界陷入了一片混亂，"]},{"code":401,"indent":1,"parameters":["儘管GOC在歐提克之戰受到了毀滅性的打擊，並且很快就解體了，"]},{"code":401,"indent":1,"parameters":["由於在這些征戰中雙方都盡力保持了克制，針對的GOC在事後的清算比起他們預料的更少。"]},{"code":250,"indent":1,"parameters":[{"name":"Book1","volume":90,"pitch":100,"pan":0}]},{"code":101,"indent":1,"parameters":["",0,1,2,""]},{"code":401,"indent":1,"parameters":["<center>在帷幕揭露後，原本處於帷幕外的人們，普遍一開始對此事感到愕然，"]},{"code":401,"indent":1,"parameters":["雙方間的矛盾還是不斷，針對超人類的迫害仍然在許多國家加劇，"]},{"code":401,"indent":1,"parameters":["某些蛇之手們所期待能平等對待他們的世界打從一開始就不可能實現。"]},{"code":250,"indent":1,"parameters":[{"name":"Book1","volume":90,"pitch":100,"pan":0}]},{"code":101,"indent":1,"parameters":["",0,1,2,""]},{"code":401,"indent":1,"parameters":["<center>但就如同蛇之手他們所期望的一樣，人們對新事物的適應速度十分之快，"]},{"code":401,"indent":1,"parameters":["耗費了十多年之久，雖然沒有贏得能真的平等對待他們的世界，"]},{"code":401,"indent":1,"parameters":["但帷幕外的人們終究還是逐漸適應了這些過往被隱藏的人們與知識，對他們更加友善了。"]},{"code":0,"indent":1,"parameters":[]},{"code":412,"indent":0,"parameters":[]},{"code":250,"indent":0,"parameters":[{"name":"Book1","volume":90,"pitch":100,"pan":0}]},{"code":101,"indent":0,"parameters":["",0,1,2,""]},{"code":401,"indent":0,"parameters":["<center>而在失去了GOC這一個長久以來抑制住敵意異常生物的組織後，"]},{"code":401,"indent":0,"parameters":["少了應對那些生物的專家後，相關的傷亡也大幅增長，"]},{"code":401,"indent":0,"parameters":["新秩序的創造者們要面對的挑戰，還有很多。"]},{"code":108,"indent":0,"parameters":["※結局2"]},{"code":408,"indent":0,"parameters":["三波特蘭的狀況"]},{"code":122,"indent":0,"parameters":[53,53,0,0,2]},{"code":122,"indent":0,"parameters":[11,11,0,0,0]},{"code":122,"indent":0,"parameters":[12,12,0,0,0]},{"code":117,"indent":0,"parameters":[13]},{"code":250,"indent":0,"parameters":[{"name":"Book1","volume":90,"pitch":100,"pan":0}]},{"code":231,"indent":0,"parameters":[99,"ending/Ending2_TPLD",1,1,11,12,100,100,0,0]},{"code":234,"indent":0,"parameters":[99,[0,0,0,255],1,false]},{"code":232,"indent":0,"parameters":[99,0,1,1,11,12,100,100,255,0,20,true,0]},{"code":108,"indent":0,"parameters":["※判斷三波特蘭的狀況"]},{"code":111,"indent":0,"parameters":[0,78,0]},{"code":101,"indent":1,"parameters":["",0,1,2,""]},{"code":401,"indent":1,"parameters":["在三波特蘭之戰後，三波特蘭受到了極其嚴重的損害，"]},{"code":401,"indent":1,"parameters":["不論是人力與財產都受到了致命的打擊。"]},{"code":250,"indent":1,"parameters":[{"name":"Book1","volume":90,"pitch":100,"pan":0}]},{"code":101,"indent":1,"parameters":["",0,1,2,""]},{"code":401,"indent":1,"parameters":["以往碰上了類似的問題都可以藉由與GOC的貿易讓經濟慢慢復甦復甦，"]},{"code":401,"indent":1,"parameters":["但在GOC已經不存在的今天，三波特蘭逐漸無法應對它財政上的缺口，"]},{"code":401,"indent":1,"parameters":["逐漸變成了一座貧窮都市。"]},{"code":250,"indent":1,"parameters":[{"name":"Book1","volume":90,"pitch":100,"pan":0}]},{"code":101,"indent":1,"parameters":["",0,1,2,""]},{"code":401,"indent":1,"parameters":["居民對這個曾經的魔幻土地感到失望，"]},{"code":401,"indent":1,"parameters":["不論市長還是市議會對此都拿不出一個有效解決方案，"]},{"code":401,"indent":1,"parameters":["於是人們逐漸向外移民，三波特蘭恐怕再也無法回歸過往的輝煌。"]},{"code":0,"indent":1,"parameters":[]},{"code":411,"indent":0,"parameters":[]},{"code":111,"indent":1,"parameters":[0,59,0]},{"code":122,"indent":2,"parameters":[6,6,0,4,"\"由於D.C. al Fine下令讓士兵們克制武力，\""]},{"code":0,"indent":2,"parameters":[]},{"code":412,"indent":1,"parameters":[]},{"code":111,"indent":1,"parameters":[0,60,0]},{"code":122,"indent":2,"parameters":[6,6,0,4,"\"由於GOC成員自發性地克制住了自身的武力，\""]},{"code":0,"indent":2,"parameters":[]},{"code":412,"indent":1,"parameters":[]},{"code":101,"indent":1,"parameters":["",0,1,2,""]},{"code":401,"indent":1,"parameters":["\\v[6]"]},{"code":401,"indent":1,"parameters":["在三波特蘭之戰後，三波特蘭受到的損害比多數人預估的更小。"]},{"code":250,"indent":1,"parameters":[{"name":"Book1","volume":90,"pitch":100,"pan":0}]},{"code":101,"indent":1,"parameters":["",0,1,2,""]},{"code":401,"indent":1,"parameters":["所以即使在在失去了這個GOC重大的貿易對象後，"]},{"code":401,"indent":1,"parameters":["三波特蘭仍蓬勃發展，成為了帷幕揭露後的一座世界著名都市。"]},{"code":250,"indent":1,"parameters":[{"name":"Book1","volume":90,"pitch":100,"pan":0}]},{"code":111,"indent":1,"parameters":[0,86,0]},{"code":101,"indent":2,"parameters":["",0,1,2,""]},{"code":401,"indent":2,"parameters":["仇恨超人類與非人類的人們針對三波特蘭的恐怖攻擊與犯罪成了新的問題，"]},{"code":401,"indent":2,"parameters":["這類惡性事件頻發也困擾了三波特蘭數十年之久。"]},{"code":0,"indent":2,"parameters":[]},{"code":411,"indent":1,"parameters":[]},{"code":111,"indent":2,"parameters":[0,86,1]},{"code":101,"indent":3,"parameters":["",0,1,2,""]},{"code":401,"indent":3,"parameters":["仇恨超人類與非人類的人們針對三波特蘭的恐怖攻擊與犯罪成了新的問題，"]},{"code":401,"indent":3,"parameters":["也有更多的人試圖消彌這些仇恨．透過運動、演說，"]},{"code":401,"indent":3,"parameters":["慈善活動等等手段，仇恨者的數量在數年後就顯著減少了。"]},{"code":111,"indent":3,"parameters":[1,28,0,6,1]},{"code":111,"indent":4,"parameters":[0,47,1]},{"code":250,"indent":5,"parameters":[{"name":"Book1","volume":90,"pitch":100,"pan":0}]},{"code":101,"indent":5,"parameters":["",0,1,2,""]},{"code":401,"indent":5,"parameters":["當中一位被稱為洛克菲勒的老人，在消彌這類仇恨時更是不惜餘力。"]},{"code":401,"indent":5,"parameters":["在他因老病故後，許多希神來到他墳前獻花，"]},{"code":401,"indent":5,"parameters":["那些希神也被確認到是哈伯希爾那場災難的受害者們。"]},{"code":0,"indent":5,"parameters":[]},{"code":412,"indent":4,"parameters":[]},{"code":0,"indent":4,"parameters":[]},{"code":412,"indent":3,"parameters":[]},{"code":0,"indent":3,"parameters":[]},{"code":412,"indent":2,"parameters":[]},{"code":0,"indent":2,"parameters":[]},{"code":412,"indent":1,"parameters":[]},{"code":0,"indent":1,"parameters":[]},{"code":412,"indent":0,"parameters":[]},{"code":108,"indent":0,"parameters":["※波動拳結束"]},{"code":408,"indent":0,"parameters":["判斷歐提克的狀況"]},{"code":122,"indent":0,"parameters":[53,53,0,0,3]},{"code":122,"indent":0,"parameters":[11,11,0,0,0]},{"code":122,"indent":0,"parameters":[12,12,0,0,0]},{"code":117,"indent":0,"parameters":[13]},{"code":231,"indent":0,"parameters":[99,"ending/Ending2_Eutec",1,1,11,12,100,100,0,0]},{"code":234,"indent":0,"parameters":[99,[0,0,0,255],1,false]},{"code":232,"indent":0,"parameters":[99,0,1,1,11,12,100,100,255,0,20,true,0]},{"code":250,"indent":0,"parameters":[{"name":"Book1","volume":90,"pitch":100,"pan":0}]},{"code":111,"indent":0,"parameters":[0,83,1]},{"code":108,"indent":1,"parameters":["※通常情況"]},{"code":111,"indent":1,"parameters":[0,86,0]},{"code":101,"indent":2,"parameters":["",0,1,2,""]},{"code":401,"indent":2,"parameters":["歐提克在被占領後，蛇之手召募的聯軍受到了長時間的游擊與抵抗，"]},{"code":401,"indent":2,"parameters":["最終在這些抵抗之下，新的統治者不得不採取高壓手段管理這座過往GOC的掌上明珠。"]},{"code":0,"indent":2,"parameters":[]},{"code":411,"indent":1,"parameters":[]},{"code":101,"indent":2,"parameters":["",0,1,2,""]},{"code":401,"indent":2,"parameters":["歐提克在被佔領後，蛇之手召募的聯軍受到了長時間的游擊與抵抗，"]},{"code":401,"indent":2,"parameters":["但他們仍然盡可能保持的克制的方式統治，儘管在一次上帝之杖的威懾性砲擊後，"]},{"code":401,"indent":2,"parameters":["仇恨者們也不得不接受自己必須與超人類們住在同一座城市的事實。"]},{"code":0,"indent":2,"parameters":[]},{"code":412,"indent":1,"parameters":[]},{"code":250,"indent":1,"parameters":[{"name":"Book1","volume":90,"pitch":100,"pan":0}]},{"code":111,"indent":1,"parameters":[0,60,0]},{"code":101,"indent":2,"parameters":["",0,1,2,""]},{"code":401,"indent":2,"parameters":["幸運的是，由於D.C. Al Fine曾下令舉辦對超人類犧牲者們的追思會，"]},{"code":401,"indent":2,"parameters":["歐提克的居民接受各式各樣超人類的速度比想像中的還要更快些，"]},{"code":401,"indent":2,"parameters":["很快地游擊隊就沒了支持者，因為金源不足而潰散。"]},{"code":0,"indent":2,"parameters":[]},{"code":411,"indent":1,"parameters":[]},{"code":250,"indent":2,"parameters":[{"name":"Book1","volume":90,"pitch":100,"pan":0}]},{"code":101,"indent":2,"parameters":["",0,1,2,""]},{"code":401,"indent":2,"parameters":["由於歐提克的居民從未真正接受過藍型以外的超人類，"]},{"code":401,"indent":2,"parameters":["游擊隊針對超人類的襲擊從未斷過，每次都造成了大量死傷，給歐提克這座城市帶來了大量混亂。"]},{"code":0,"indent":2,"parameters":[]},{"code":412,"indent":1,"parameters":[]},{"code":250,"indent":1,"parameters":[{"name":"Book1","volume":90,"pitch":100,"pan":0}]},{"code":111,"indent":1,"parameters":[8,58]},{"code":101,"indent":2,"parameters":["",0,1,2,""]},{"code":401,"indent":2,"parameters":["游擊隊的領導者\\c[6]貝恩德‧泰勒\\c[0]是因為因為自己親生女兒的出賣而被捕的，"]},{"code":401,"indent":2,"parameters":["但他在法庭上聲稱沒有對自己的所作所為有一絲後悔，"]},{"code":401,"indent":2,"parameters":["並強調自己的所謂所為：「都是為了讓世界回歸正常」。"]},{"code":0,"indent":2,"parameters":[]},{"code":411,"indent":1,"parameters":[]},{"code":101,"indent":2,"parameters":["",0,1,2,""]},{"code":401,"indent":2,"parameters":["游擊隊的領導者\\c[6]貝恩德‧泰勒\\c[0]仍然在逃，"]},{"code":401,"indent":2,"parameters":["至今當局尚無阻止他的方法。"]},{"code":0,"indent":2,"parameters":[]},{"code":412,"indent":1,"parameters":[]},{"code":250,"indent":1,"parameters":[{"name":"Book1","volume":90,"pitch":100,"pan":0}]},{"code":101,"indent":1,"parameters":["",0,1,2,""]},{"code":401,"indent":1,"parameters":["除了游擊隊，長久以來的貧富差距問題也成了新的統治者頭疼的問題，"]},{"code":401,"indent":1,"parameters":["歐提克這座都市仍需要相當大的時間去改善。"]},{"code":0,"indent":1,"parameters":[]},{"code":411,"indent":0,"parameters":[]},{"code":108,"indent":1,"parameters":["※歐提克毀滅了"]},{"code":101,"indent":1,"parameters":["",0,1,2,""]},{"code":401,"indent":1,"parameters":["由於現實扭曲者約書亞‧米茲蠟希的作為，歐提克毀滅了，"]},{"code":401,"indent":1,"parameters":["口袋空間被徹底撕裂，當中九成人口喪生，"]},{"code":401,"indent":1,"parameters":["而整個世界永遠會記住蛇之手在當天做了什麼。"]},{"code":0,"indent":1,"parameters":[]},{"code":412,"indent":0,"parameters":[]},{"code":108,"indent":0,"parameters":["※伊瓦迪村的狀況"]},{"code":122,"indent":0,"parameters":[53,53,0,0,4]},{"code":122,"indent":0,"parameters":[11,11,0,0,0]},{"code":122,"indent":0,"parameters":[12,12,0,0,0]},{"code":117,"indent":0,"parameters":[13]},{"code":231,"indent":0,"parameters":[99,"ending/Ending3_Ivady",1,1,11,12,100,100,0,0]},{"code":234,"indent":0,"parameters":[99,[0,0,0,255],1,false]},{"code":232,"indent":0,"parameters":[99,0,1,1,11,12,100,100,255,0,20,true,0]},{"code":250,"indent":0,"parameters":[{"name":"Book1","volume":90,"pitch":100,"pan":0}]},{"code":108,"indent":0,"parameters":["※判斷伊瓦迪村的狀況"]},{"code":108,"indent":0,"parameters":["※金莉任務有無作完"]},{"code":101,"indent":0,"parameters":["",0,1,2,""]},{"code":401,"indent":0,"parameters":["伊瓦迪村在遭受GOC襲擊後，幾乎所有村中孩童死亡，聖樹也被摧毀，"]},{"code":401,"indent":0,"parameters":["村中原本的希望\\n[14]也死於GOC槍下，原本和瑪納慈善基金會合作的他們再也沒有本錢那麼做了。"]},{"code":250,"indent":0,"parameters":[{"name":"Book1","volume":90,"pitch":100,"pan":0}]},{"code":111,"indent":0,"parameters":[1,31,0,5,1]},{"code":101,"indent":1,"parameters":["",0,1,2,""]},{"code":401,"indent":1,"parameters":["然而事情兩年之後似乎有所轉機，"]},{"code":401,"indent":1,"parameters":["一棵新的聖樹在聖地長了出來，並且擁有與被燒毀那座類似的性質，村民再次找回了希望。"]},{"code":250,"indent":1,"parameters":[{"name":"Book1","volume":90,"pitch":100,"pan":0}]},{"code":101,"indent":1,"parameters":["",0,1,2,""]},{"code":401,"indent":1,"parameters":["這一次村民們終於理解他們傳說的由來，"]},{"code":401,"indent":1,"parameters":["儘管他們仍舊崇敬大術士伊仰，但他們崇敬的人又多了一位伊瓦迪‧金莉。"]},{"code":250,"indent":1,"parameters":[{"name":"Book1","volume":90,"pitch":100,"pan":0}]},{"code":101,"indent":1,"parameters":["",0,1,2,""]},{"code":401,"indent":1,"parameters":["儘管在漫長的歷史中他們失去了前一棵聖樹的本名，"]},{"code":401,"indent":1,"parameters":["但這一次他們打算永遠記下聖樹生前的名字。"]},{"code":0,"indent":1,"parameters":[]},{"code":411,"indent":0,"parameters":[]},{"code":250,"indent":1,"parameters":[{"name":"Book1","volume":90,"pitch":100,"pan":0}]},{"code":101,"indent":1,"parameters":["",0,1,2,""]},{"code":401,"indent":1,"parameters":["在這三重打擊之下村民們沒有回到自己的故鄉，"]},{"code":401,"indent":1,"parameters":["而是選擇在別處生活，伊瓦迪村不久後就成為了廢村。"]},{"code":0,"indent":1,"parameters":[]},{"code":412,"indent":0,"parameters":[]},{"code":108,"indent":0,"parameters":["※哈柏希爾的狀況"]},{"code":122,"indent":0,"parameters":[53,53,0,0,5]},{"code":122,"indent":0,"parameters":[11,11,0,0,0]},{"code":122,"indent":0,"parameters":[12,12,0,0,0]},{"code":117,"indent":0,"parameters":[13]},{"code":231,"indent":0,"parameters":[99,"ending/Ending4_HyBrasil",1,1,11,12,100,100,0,0]},{"code":234,"indent":0,"parameters":[99,[0,0,0,255],1,false]},{"code":232,"indent":0,"parameters":[99,0,1,1,11,12,100,100,255,0,20,true,0]},{"code":250,"indent":0,"parameters":[{"name":"Book1","volume":90,"pitch":100,"pan":0}]},{"code":111,"indent":0,"parameters":[0,56,1]},{"code":101,"indent":1,"parameters":["13.others4",2,1,2,""]},{"code":401,"indent":1,"parameters":["因為\\n[8]的手下留情，魯格四世活了下來，"]},{"code":401,"indent":1,"parameters":["這個野心家不會屈服於牢獄之災，在蛇之手與GOC都離開島上後，"]},{"code":401,"indent":1,"parameters":["他抓準時機又來了一次裡應外合，成功發動了政變。"]},{"code":250,"indent":1,"parameters":[{"name":"Book1","volume":90,"pitch":100,"pan":0}]},{"code":101,"indent":1,"parameters":["13.others4",2,1,2,""]},{"code":401,"indent":1,"parameters":["德爾貝斯成為了階下囚，而在新國王領導下的國家陷入了長久的暴政之中，"]},{"code":401,"indent":1,"parameters":["雖是對反對派毫不留情的暴政，但國家的經濟發展在他積極對外交流的狀況下還是獲得"]},{"code":401,"indent":1,"parameters":["了飛速提升，不論是國民生活品質或是科技水準都變得更勝以往。"]},{"code":250,"indent":1,"parameters":[{"name":"Book1","volume":90,"pitch":100,"pan":0}]},{"code":101,"indent":1,"parameters":["13.others4",2,1,2,""]},{"code":401,"indent":1,"parameters":["許多傳統的陋習與不合時宜的法律也在他領導下接連被國民拋棄，"]},{"code":401,"indent":1,"parameters":["他的改革無疑是成功的，但他的血腥手段仍遭致不少批評。"]},{"code":250,"indent":1,"parameters":[{"name":"Book1","volume":90,"pitch":100,"pan":0}]},{"code":111,"indent":1,"parameters":[0,39,1]},{"code":101,"indent":2,"parameters":["13.others4",2,1,2,""]},{"code":401,"indent":2,"parameters":["然而在他以血腥手段砍除了大量國家陋習與陳腐思想後，又於晚年一步步的放開自"]},{"code":401,"indent":2,"parameters":["身權力，哈伯希爾最終被他改革成了一個君主立憲的民主國家，"]},{"code":401,"indent":2,"parameters":[""]},{"code":401,"indent":2,"parameters":["有人說這都是在一次與身分不明的蛇之手成員交談後的所做的決定。"]},{"code":250,"indent":2,"parameters":[{"name":"Book1","volume":90,"pitch":100,"pan":0}]},{"code":101,"indent":2,"parameters":["13.others4",2,1,2,""]},{"code":401,"indent":2,"parameters":["照理說這麼重大的變動應該會招致強烈反彈，"]},{"code":401,"indent":2,"parameters":["但哈伯希爾早就已經沒人能違抗他了。"]},{"code":0,"indent":2,"parameters":[]},{"code":411,"indent":1,"parameters":[]},{"code":101,"indent":2,"parameters":["13.others4",2,1,2,""]},{"code":401,"indent":2,"parameters":["儘管在魯格的領導下哈伯希爾變得強所未有的強盛與富裕，"]},{"code":401,"indent":2,"parameters":["這位獨裁者終究沒能培養出和他一樣優秀的繼承人，"]},{"code":401,"indent":2,"parameters":["在他死後國家又陷入王位之爭的混亂，而在新王登基後，沒多久就將他多年的建樹全都浪費掉了。"]},{"code":0,"indent":2,"parameters":[]},{"code":412,"indent":1,"parameters":[]},{"code":0,"indent":1,"parameters":[]},{"code":411,"indent":0,"parameters":[]},{"code":101,"indent":1,"parameters":["23.Others7",4,1,2,""]},{"code":401,"indent":1,"parameters":["哈伯希爾在魯格王子死後，國內再也無人能真正與國王德爾貝斯二世抗衡，"]},{"code":401,"indent":1,"parameters":["於是在國王的命令下，那個曾經招來大海怪的防護塔被再次建了起來，"]},{"code":401,"indent":1,"parameters":["整個哈伯希爾在經濟陷入頹勢的狀況下，等待著下個一千年的大災難。"]},{"code":250,"indent":1,"parameters":[{"name":"Book1","volume":90,"pitch":100,"pan":0}]},{"code":101,"indent":1,"parameters":["23.Others7",4,1,2,""]},{"code":401,"indent":1,"parameters":["至於一千年後哈伯希爾又會發生什麼大災難，誰在乎呢？"]},{"code":401,"indent":1,"parameters":["反正在那時德爾貝斯王早已不在王座上了。"]},{"code":0,"indent":1,"parameters":[]},{"code":412,"indent":0,"parameters":[]},{"code":108,"indent":0,"parameters":["※米茲蠟希的狀況"]},{"code":108,"indent":0,"parameters":["※判斷米茲蠟希否存活"]},{"code":408,"indent":0,"parameters":["０為存活"]},{"code":122,"indent":0,"parameters":[6,6,0,0,0]},{"code":111,"indent":0,"parameters":[0,46,0]},{"code":122,"indent":1,"parameters":[6,6,0,0,1]},{"code":0,"indent":1,"parameters":[]},{"code":412,"indent":0,"parameters":[]},{"code":111,"indent":0,"parameters":[1,38,0,5,1]},{"code":122,"indent":1,"parameters":[6,6,0,0,1]},{"code":0,"indent":1,"parameters":[]},{"code":412,"indent":0,"parameters":[]},{"code":250,"indent":0,"parameters":[{"name":"Book1","volume":90,"pitch":100,"pan":0}]},{"code":122,"indent":0,"parameters":[53,53,0,0,6]},{"code":122,"indent":0,"parameters":[11,11,0,0,0]},{"code":122,"indent":0,"parameters":[12,12,0,0,0]},{"code":117,"indent":0,"parameters":[13]},{"code":231,"indent":0,"parameters":[99,"ending/Ending5_Mizrahi",1,1,11,12,100,100,0,0]},{"code":234,"indent":0,"parameters":[99,[0,0,0,255],1,false]},{"code":232,"indent":0,"parameters":[99,0,1,1,11,12,100,100,255,0,20,true,0]},{"code":111,"indent":0,"parameters":[1,6,0,0,0]},{"code":101,"indent":1,"parameters":["18.Child_God_.Joshua",0,1,2,""]},{"code":401,"indent":1,"parameters":["儘管他的極端作為惹惱了數不清的勢力，"]},{"code":401,"indent":1,"parameters":["約書亞‧米茲蠟希這位幼稚之神還是存活了下來。"]},{"code":111,"indent":1,"parameters":[0,86,0]},{"code":250,"indent":2,"parameters":[{"name":"Book1","volume":90,"pitch":100,"pan":0}]},{"code":101,"indent":2,"parameters":["18.Child_God_.Joshua",0,1,2,""]},{"code":401,"indent":2,"parameters":["在數年給造成更多麻煩甚至傷亡後，"]},{"code":401,"indent":2,"parameters":["這位瘋狂的現實扭曲者建立了屬於自己的國家，"]},{"code":401,"indent":2,"parameters":["一個仰賴奴役與剝削基準人類運作的恐怖國度。"]},{"code":111,"indent":2,"parameters":[0,83,0]},{"code":250,"indent":3,"parameters":[{"name":"Book1","volume":90,"pitch":100,"pan":0}]},{"code":101,"indent":3,"parameters":["18.Child_God_.Joshua",0,1,2,""]},{"code":401,"indent":3,"parameters":["摧毀歐提克使得米茲蠟希聲名大噪，"]},{"code":401,"indent":3,"parameters":["大量與他理念相近的追隨者成為了他的部屬。"]},{"code":0,"indent":3,"parameters":[]},{"code":412,"indent":2,"parameters":[]},{"code":250,"indent":2,"parameters":[{"name":"Book1","volume":90,"pitch":100,"pan":0}]},{"code":101,"indent":2,"parameters":["18.Child_God_.Joshua",0,1,2,""]},{"code":401,"indent":2,"parameters":["儘管許多蛇之手都不滿他的作為，"]},{"code":401,"indent":2,"parameters":["但不可否認的是許多人都需要這名幼稚之神的強大力量。"]},{"code":0,"indent":2,"parameters":[]},{"code":411,"indent":1,"parameters":[]},{"code":250,"indent":2,"parameters":[{"name":"Book1","volume":90,"pitch":100,"pan":0}]},{"code":101,"indent":2,"parameters":["18.Child_God_.Joshua",0,1,2,""]},{"code":401,"indent":2,"parameters":["在十數年來給其他蛇之手造成更多傷亡後，"]},{"code":401,"indent":2,"parameters":["這位瘋狂的現實扭曲者才終於在付出慘痛代價下被蛇之手們聯合剿滅。"]},{"code":0,"indent":2,"parameters":[]},{"code":412,"indent":1,"parameters":[]},{"code":0,"indent":1,"parameters":[]},{"code":411,"indent":0,"parameters":[]},{"code":101,"indent":1,"parameters":["18.Child_God_.Joshua",0,1,2,""]},{"code":401,"indent":1,"parameters":["米茲蠟希這位強大的現實扭曲者死了，似乎在向其他現實扭曲者表明了一件事，"]},{"code":401,"indent":1,"parameters":["即便你有多麼強大的力量，惹惱了太多人之後還是會被幹掉的。"]},{"code":0,"indent":1,"parameters":[]},{"code":412,"indent":0,"parameters":[]},{"code":108,"indent":0,"parameters":["※SCP基金會的狀況"]},{"code":205,"indent":0,"parameters":[2,{"list":[{"code":41,"parameters":["04.others2",2],"indent":null},{"code":0}],"repeat":false,"skippable":false,"wait":true}]},{"code":505,"indent":0,"parameters":[{"code":41,"parameters":["04.others2",2],"indent":null}]},{"code":122,"indent":0,"parameters":[53,53,0,0,7]},{"code":122,"indent":0,"parameters":[11,11,0,0,0]},{"code":122,"indent":0,"parameters":[12,12,0,0,0]},{"code":117,"indent":0,"parameters":[13]},{"code":231,"indent":0,"parameters":[99,"SCP_Foundation_Logo",1,1,11,12,100,100,0,0]},{"code":234,"indent":0,"parameters":[99,[0,0,0,255],1,false]},{"code":232,"indent":0,"parameters":[99,0,1,1,11,12,100,100,255,0,20,true,0]},{"code":111,"indent":0,"parameters":[0,86,0]},{"code":122,"indent":1,"parameters":[6,6,0,4,"\"基金會也不至於成為蛇之手的敵人。\""]},{"code":0,"indent":1,"parameters":[]},{"code":411,"indent":0,"parameters":[]},{"code":122,"indent":1,"parameters":[6,6,0,4,"\"基金會仍能與蛇之手在某種程度上合作。\""]},{"code":0,"indent":1,"parameters":[]},{"code":412,"indent":0,"parameters":[]},{"code":250,"indent":0,"parameters":[{"name":"Book1","volume":90,"pitch":100,"pan":0}]},{"code":111,"indent":0,"parameters":[0,51,1]},{"code":101,"indent":1,"parameters":["",0,1,2,""]},{"code":401,"indent":1,"parameters":["得益於蛇之手盡可能沒有與基金會撕破臉，"]},{"code":401,"indent":1,"parameters":["在帷幕撕裂後，\\v[6]"]},{"code":111,"indent":1,"parameters":[0,86,1]},{"code":250,"indent":2,"parameters":[{"name":"Book1","volume":90,"pitch":100,"pan":0}]},{"code":101,"indent":2,"parameters":["",0,1,2,""]},{"code":401,"indent":2,"parameters":["基金會在帷幕揭露後工作內容改變了，他們變成更加公開的組織，"]},{"code":401,"indent":2,"parameters":["不只獲得更多資源保護人類不受異常所害，也更加重視保護異常不受人類所害的任務上。"]},{"code":0,"indent":2,"parameters":[]},{"code":412,"indent":1,"parameters":[]},{"code":0,"indent":1,"parameters":[]},{"code":411,"indent":0,"parameters":[]},{"code":101,"indent":1,"parameters":["",0,1,2,""]},{"code":401,"indent":1,"parameters":["蛇之手與基金會撕破臉的後果就是在帷幕撕裂後，"]},{"code":401,"indent":1,"parameters":["基金會徹頭徹尾成為了蛇之手的敵人，過往的獄卒們這次真的期望帷幕再次回來。"]},{"code":0,"indent":1,"parameters":[]},{"code":412,"indent":0,"parameters":[]},{"code":250,"indent":0,"parameters":[{"name":"Book1","volume":90,"pitch":100,"pan":0}]},{"code":101,"indent":0,"parameters":["",0,1,2,""]},{"code":401,"indent":0,"parameters":["過往使用D級人員與囚禁綁架超人類的歷史給他們留下了一筆漫長的人權劣跡，"]},{"code":401,"indent":0,"parameters":["在帷幕揭露後他們也因受到公眾強烈批判，迫於壓力下、基金會也不得不努力改善這問題。"]},{"code":108,"indent":0,"parameters":["※奧蕾絲的狀況的狀況，如果存活。"]},{"code":111,"indent":0,"parameters":[8,33]},{"code":108,"indent":1,"parameters":["※奧蕾絲的狀況的狀況，如果存活。"]},{"code":205,"indent":1,"parameters":[2,{"list":[{"code":41,"parameters":["4666",1],"indent":null},{"code":0}],"repeat":false,"skippable":false,"wait":true}]},{"code":505,"indent":1,"parameters":[{"code":41,"parameters":["4666",1],"indent":null}]},{"code":122,"indent":1,"parameters":[53,53,0,0,8]},{"code":122,"indent":1,"parameters":[11,11,0,0,0]},{"code":122,"indent":1,"parameters":[12,12,0,0,0]},{"code":117,"indent":1,"parameters":[13]},{"code":231,"indent":1,"parameters":[99,"ending/Ending6_Orlaith",1,1,11,12,100,100,0,0]},{"code":234,"indent":1,"parameters":[99,[0,0,0,255],1,false]},{"code":232,"indent":1,"parameters":[99,0,1,1,11,12,100,100,255,0,20,true,0]},{"code":108,"indent":1,"parameters":["※奧蕾絲的狀況的狀況，是否有戀愛關係。"]},{"code":111,"indent":1,"parameters":[0,84,0]},{"code":111,"indent":2,"parameters":[0,86,0]},{"code":122,"indent":3,"parameters":[6,6,0,4,"\"成為了蛇之手的敵人，儘管光憑她的力量根本激不起什麼浪花，很快就輕易戰死了。\""]},{"code":0,"indent":3,"parameters":[]},{"code":411,"indent":2,"parameters":[]},{"code":122,"indent":3,"parameters":[6,6,0,4,"\"用自己的餘生控訴著戰爭的殘酷，成為了反戰組織的一員。\""]},{"code":0,"indent":3,"parameters":[]},{"code":412,"indent":2,"parameters":[]},{"code":250,"indent":2,"parameters":[{"name":"Book1","volume":90,"pitch":100,"pan":0}]},{"code":122,"indent":2,"parameters":[6,6,0,4,"\"成為了蛇之手的敵人，儘管光憑她的力量根本激不起什麼浪花，很快就輕易戰死了。\""]},{"code":101,"indent":2,"parameters":["10.Orlaith",2,1,2,""]},{"code":401,"indent":2,"parameters":["曾經的蛇巢領導\\n[11]如今因愛人身亡，"]},{"code":401,"indent":2,"parameters":["\\v[6]"]},{"code":0,"indent":2,"parameters":[]},{"code":412,"indent":1,"parameters":[]},{"code":111,"indent":1,"parameters":[0,85,1]},{"code":111,"indent":2,"parameters":[8,47]},{"code":250,"indent":3,"parameters":[{"name":"Book1","volume":90,"pitch":100,"pan":0}]},{"code":101,"indent":3,"parameters":["10.Orlaith",5,1,2,""]},{"code":401,"indent":3,"parameters":["曾經的蛇巢領導\\n[11]退出蛇之手了，"]},{"code":401,"indent":3,"parameters":["現在的她與她的新丈夫在她的小木屋隱居著，所幸他在審判中倖存。"]},{"code":250,"indent":3,"parameters":[{"name":"Book1","volume":90,"pitch":100,"pan":0}]},{"code":101,"indent":3,"parameters":["10.Orlaith",4,1,2,""]},{"code":401,"indent":3,"parameters":["這個人類丈夫與身為希神的她是不會有後代的，"]},{"code":401,"indent":3,"parameters":["但對喪夫而寂寞太久的她，或許這件事是一件好事？"]},{"code":401,"indent":3,"parameters":[""]},{"code":401,"indent":3,"parameters":["也因此苦了他的丈夫了。"]},{"code":0,"indent":3,"parameters":[]},{"code":411,"indent":2,"parameters":[]},{"code":108,"indent":3,"parameters":["※奧蕾絲的狀況的狀況，是否有戀愛關係。"]},{"code":250,"indent":3,"parameters":[{"name":"Book1","volume":90,"pitch":100,"pan":0}]},{"code":101,"indent":3,"parameters":["10.Orlaith",5,1,2,""]},{"code":401,"indent":3,"parameters":["曾經的蛇巢領導\\n[11]回到了自己故鄉哈伯希爾，"]},{"code":401,"indent":3,"parameters":["並試圖為重建它做些什麼。"]},{"code":0,"indent":3,"parameters":[]},{"code":412,"indent":2,"parameters":[]},{"code":0,"indent":2,"parameters":[]},{"code":412,"indent":1,"parameters":[]},{"code":0,"indent":1,"parameters":[]},{"code":412,"indent":0,"parameters":[]},{"code":108,"indent":0,"parameters":["※敗者首領的狀況"]},{"code":122,"indent":0,"parameters":[53,53,0,0,8]},{"code":122,"indent":0,"parameters":[11,11,0,0,0]},{"code":122,"indent":0,"parameters":[12,12,0,0,0]},{"code":117,"indent":0,"parameters":[13]},{"code":231,"indent":0,"parameters":[99,"ending/Ending7_AL_FINE",1,1,11,12,100,100,0,0]},{"code":234,"indent":0,"parameters":[99,[0,0,0,255],1,false]},{"code":232,"indent":0,"parameters":[99,0,1,1,11,12,100,100,255,0,20,true,0]},{"code":250,"indent":0,"parameters":[{"name":"Book1","volume":90,"pitch":100,"pan":0}]},{"code":101,"indent":0,"parameters":["26.DC_al_fine",0,1,2,""]},{"code":401,"indent":0,"parameters":["D.C. Al Fine，聯盟最高領導者，議長兼副祕書長，"]},{"code":401,"indent":0,"parameters":["在歐提克之戰時不知所蹤，有人說她早已預料到這次的失敗，所以趁亂逃跑。"]},{"code":250,"indent":0,"parameters":[{"name":"Book1","volume":90,"pitch":100,"pan":0}]},{"code":101,"indent":0,"parameters":["26.DC_al_fine",0,1,2,""]},{"code":401,"indent":0,"parameters":["但蛇之手在突襲她的據點後獲得了她本人的錄音，內容大致如下："]},{"code":401,"indent":0,"parameters":["「第4267次避免人類毀滅之嘗試已宣告失敗，但成功維持帷幕超過70年，"]},{"code":401,"indent":0,"parameters":["帷幕已無重建可能，因此這一條時間線應被放棄，接下來進行第4268次嘗試。」"]},{"code":232,"indent":0,"parameters":[99,0,1,1,11,12,100,100,0,0,20,true,0]},{"code":108,"indent":0,"parameters":["※主角群"]},{"code":108,"indent":0,"parameters":["※伊沃爾的場合"]},{"code":235,"indent":0,"parameters":[99]},{"code":108,"indent":0,"parameters":["※伊沃爾如果相關任務解到可能導致壞結局"]},{"code":408,"indent":0,"parameters":["之後可以放立繪。"]},{"code":122,"indent":0,"parameters":[6,6,0,0,0]},{"code":111,"indent":0,"parameters":[1,32,0,3,1]},{"code":122,"indent":1,"parameters":[6,6,1,0,1]},{"code":0,"indent":1,"parameters":[]},{"code":412,"indent":0,"parameters":[]},{"code":111,"indent":0,"parameters":[0,47,1]},{"code":122,"indent":1,"parameters":[6,6,1,0,1]},{"code":0,"indent":1,"parameters":[]},{"code":412,"indent":0,"parameters":[]},{"code":111,"indent":0,"parameters":[0,56,1]},{"code":122,"indent":1,"parameters":[6,6,1,0,1]},{"code":0,"indent":1,"parameters":[]},{"code":412,"indent":0,"parameters":[]},{"code":111,"indent":0,"parameters":[0,52,0]},{"code":122,"indent":1,"parameters":[6,6,1,0,1]},{"code":0,"indent":1,"parameters":[]},{"code":412,"indent":0,"parameters":[]},{"code":231,"indent":0,"parameters":[99,"Actor8_Iomhar_menu",0,0,690,140,100,100,0,0]},{"code":232,"indent":0,"parameters":[99,0,0,0,620,140,100,100,255,0,30,false,0]},{"code":250,"indent":0,"parameters":[{"name":"Book1","volume":90,"pitch":100,"pan":0}]},{"code":111,"indent":0,"parameters":[1,6,0,3,3]},{"code":108,"indent":1,"parameters":["※心靈的平靜"]},{"code":101,"indent":1,"parameters":["",4,1,2,""]},{"code":401,"indent":1,"parameters":["這趟旅程讓\\n[8]明白了，"]},{"code":401,"indent":1,"parameters":["有時仍有必要忍耐自身的憤怒，他放下了武器，試圖培養一群比起殺戮更重視救人"]},{"code":401,"indent":1,"parameters":["的「騎士」們，儘管忘不掉他的學生，時而還是會因惡夢中驚醒。"]},{"code":250,"indent":1,"parameters":[{"name":"Book1","volume":90,"pitch":100,"pan":0}]},{"code":101,"indent":1,"parameters":["",4,1,2,""]},{"code":401,"indent":1,"parameters":["而他的新一批學生成為了他的支柱，"]},{"code":401,"indent":1,"parameters":["這一次沒有人再從他身邊奪去他們了。"]},{"code":250,"indent":1,"parameters":[{"name":"Book1","volume":90,"pitch":100,"pan":0}]},{"code":101,"indent":1,"parameters":["",4,1,2,""]},{"code":401,"indent":1,"parameters":["不論他生前如何，"]},{"code":401,"indent":1,"parameters":["在這名老者逝去時的表情看上去十分安詳，就好像已經找到了心靈的平靜一樣。"]},{"code":0,"indent":1,"parameters":[]},{"code":411,"indent":0,"parameters":[]},{"code":108,"indent":1,"parameters":["※心靈的不安"]},{"code":101,"indent":1,"parameters":["",7,1,2,""]},{"code":401,"indent":1,"parameters":["儘管成功撕裂的帷幕，\\n[8]仍沉浸在學生被殺的憤怒之中，"]},{"code":401,"indent":1,"parameters":["不論做什麼都無法緩解他的憤怒，狩獵焚書人的「正義執行」活動仍在進行中。"]},{"code":108,"indent":1,"parameters":["※判斷米茲蠟希否存活"]},{"code":408,"indent":1,"parameters":["0為存活"]},{"code":111,"indent":1,"parameters":[0,86,0]},{"code":122,"indent":2,"parameters":[6,6,0,0,0]},{"code":111,"indent":2,"parameters":[0,46,0]},{"code":122,"indent":3,"parameters":[6,6,0,0,1]},{"code":0,"indent":3,"parameters":[]},{"code":412,"indent":2,"parameters":[]},{"code":111,"indent":2,"parameters":[1,38,0,5,1]},{"code":122,"indent":3,"parameters":[6,6,0,0,1]},{"code":0,"indent":3,"parameters":[]},{"code":412,"indent":2,"parameters":[]},{"code":108,"indent":2,"parameters":["加入米茲蠟希"]},{"code":111,"indent":2,"parameters":[1,6,0,0,1]},{"code":250,"indent":3,"parameters":[{"name":"Book1","volume":90,"pitch":100,"pan":0}]},{"code":101,"indent":3,"parameters":["03.SH1",7,1,2,""]},{"code":401,"indent":3,"parameters":["最終他加入了米茲蠟希與他的國度，"]},{"code":401,"indent":3,"parameters":["成為他底下的得力殺手。"]},{"code":0,"indent":3,"parameters":[]},{"code":412,"indent":2,"parameters":[]},{"code":0,"indent":2,"parameters":[]},{"code":412,"indent":1,"parameters":[]},{"code":0,"indent":1,"parameters":[]},{"code":412,"indent":0,"parameters":[]},{"code":108,"indent":0,"parameters":["※消除圖片"]},{"code":232,"indent":0,"parameters":[99,0,0,0,690,140,100,100,0,0,30,false,0]},{"code":108,"indent":0,"parameters":["※若霜與美咲的場合"]},{"code":122,"indent":0,"parameters":[53,53,0,0,8]},{"code":231,"indent":0,"parameters":[99,"Actor7_RUO_SHUANG_menu",0,0,690,150,100,100,0,0]},{"code":231,"indent":0,"parameters":[98,"Actor6_Misaki_menu",0,0,160,150,100,100,0,0]},{"code":232,"indent":0,"parameters":[99,0,0,0,660,150,100,100,255,0,30,false,0]},{"code":232,"indent":0,"parameters":[98,0,0,0,190,150,100,100,255,0,30,true,0]},{"code":250,"indent":0,"parameters":[{"name":"Book1","volume":90,"pitch":100,"pan":0}]},{"code":111,"indent":0,"parameters":[0,86,1]},{"code":101,"indent":1,"parameters":["",7,1,2,""]},{"code":401,"indent":1,"parameters":["幸運的是，由於大家的努力，在帷幕被撕裂後秩序很快被重建，"]},{"code":401,"indent":1,"parameters":["\\n[6]和\\n[7]隨後便在三波特蘭舉辦了先前因GOC而被延期的婚禮，"]},{"code":401,"indent":1,"parameters":["這對妻妻在當地過著羨煞旁人的生活。"]},{"code":250,"indent":1,"parameters":[{"name":"Book1","volume":90,"pitch":100,"pan":0}]},{"code":101,"indent":1,"parameters":["07.SH4",4,1,2,""]},{"code":401,"indent":1,"parameters":["\\n[7]在結婚後不久很快就懷孕了，"]},{"code":401,"indent":1,"parameters":["兩人之間有了孩子，由於兩人的性別都是女性，不免傳出了點謠言。"]},{"code":250,"indent":1,"parameters":[{"name":"Book1","volume":90,"pitch":100,"pan":0}]},{"code":101,"indent":1,"parameters":["07.SH4",2,1,2,""]},{"code":401,"indent":1,"parameters":["當朋友問起\\n[6]這是怎麼回事時，她的回答則是："]},{"code":401,"indent":1,"parameters":["「不是領養、也沒有借精，那孩子是我們倆的親骨肉，"]},{"code":401,"indent":1,"parameters":["不要忘記\\n[7]是現實扭曲者，我們在結婚前也偶爾會那麼做。」"]},{"code":250,"indent":1,"parameters":[{"name":"Book1","volume":90,"pitch":100,"pan":0}]},{"code":101,"indent":1,"parameters":["07.SH4",4,1,2,""]},{"code":401,"indent":1,"parameters":["\\n[7]因為過往的事蹟，在包含市長在內人們的簇擁下參選成為了三波特蘭的議員，"]},{"code":401,"indent":1,"parameters":["儘管她有相當高的支持率，但在幾年後很快就後悔了，"]},{"code":401,"indent":1,"parameters":["因為能陪伴家人的時間還是比想像中少。"]},{"code":250,"indent":1,"parameters":[{"name":"Book1","volume":90,"pitch":100,"pan":0}]},{"code":111,"indent":1,"parameters":[1,33,0,4,1]},{"code":101,"indent":2,"parameters":["07.SH4",3,1,2,""]},{"code":401,"indent":2,"parameters":["\\n[6]繼承了烏拉瑪齊‧睦美在三波特蘭的壽司店，"]},{"code":401,"indent":2,"parameters":["她深知自身仍需要在壽司之道上修練，但她還是成為了夢想中的壽司師傅。"]},{"code":0,"indent":2,"parameters":[]},{"code":411,"indent":1,"parameters":[]},{"code":101,"indent":2,"parameters":["04.SH2",0,1,2,""]},{"code":401,"indent":2,"parameters":["\\n[6]成為了蛇巢領導後，因為事務繁忙，"]},{"code":401,"indent":2,"parameters":["退出了沙皇先知協會，現在的她的任務就是協調在三波特蘭許多超人類與基準人類之間的紛爭。"]},{"code":0,"indent":2,"parameters":[]},{"code":412,"indent":1,"parameters":[]},{"code":0,"indent":1,"parameters":[]},{"code":411,"indent":0,"parameters":[]},{"code":101,"indent":1,"parameters":["",7,1,2,""]},{"code":401,"indent":1,"parameters":["即便帷幕已被撕裂、GOC也已倒台。"]},{"code":401,"indent":1,"parameters":["\\n[7]和\\n[6]發覺局勢仍沒有緩和的跡象，反而更加混亂。"]},{"code":250,"indent":1,"parameters":[{"name":"Book1","volume":90,"pitch":100,"pan":0}]},{"code":101,"indent":1,"parameters":["",7,1,2,""]},{"code":401,"indent":1,"parameters":["兩人為了和平四處奔走，"]},{"code":401,"indent":1,"parameters":["原本因為GOC襲擊而延期的婚禮因為類似理由不斷一延再延，混亂持續的時間意外的長，"]},{"code":401,"indent":1,"parameters":["這對情侶開始懷疑是否即使耗費完了彼此的一生，也都沒辦法得到一場滿意的婚禮。"]},{"code":111,"indent":1,"parameters":[0,39,0]},{"code":250,"indent":2,"parameters":[{"name":"Book1","volume":90,"pitch":100,"pan":0}]},{"code":101,"indent":2,"parameters":["",7,1,2,""]},{"code":401,"indent":2,"parameters":["更為糟糕的是，不如\\n[12]生前所期望的那樣，"]},{"code":401,"indent":2,"parameters":["\\n[7]原本的領導：緁爾汀‧法蘭希斯‧布徹最終成為了一位暴虐的統治者，"]},{"code":401,"indent":2,"parameters":["兩人曾宣告大眾，為了阻止這位新誕生的幼稚之神將去挑戰她，隨後便再也沒有人見到兩人的蹤影了。"]},{"code":0,"indent":2,"parameters":[]},{"code":412,"indent":1,"parameters":[]},{"code":0,"indent":1,"parameters":[]},{"code":412,"indent":0,"parameters":[]},{"code":108,"indent":0,"parameters":["※消除圖片"]},{"code":232,"indent":0,"parameters":[99,0,0,0,690,150,100,100,0,0,30,false,0]},{"code":232,"indent":0,"parameters":[98,0,0,0,170,150,100,100,0,0,30,true,0]},{"code":108,"indent":0,"parameters":["趙禎的場合"]},{"code":231,"indent":0,"parameters":[99,"Actor5_ZHAO_ZHEN_menu",0,0,510,120,100,100,0,0]},{"code":232,"indent":0,"parameters":[99,0,0,0,490,120,100,100,255,0,30,true,0]},{"code":250,"indent":0,"parameters":[{"name":"Book1","volume":90,"pitch":100,"pan":0}]},{"code":250,"indent":0,"parameters":[{"name":"Book1","volume":90,"pitch":100,"pan":0}]},{"code":111,"indent":0,"parameters":[1,31,0,5,4]},{"code":108,"indent":1,"parameters":["※如果未曾解過金莉教授等納勒迦系列的任務，"]},{"code":408,"indent":1,"parameters":["將在故事結束後兩年因為沒有經過對身體的調整而身體無法承受進一步的突變而死亡"]},{"code":101,"indent":1,"parameters":["03.SH1",2,1,2,""]},{"code":401,"indent":1,"parameters":["很可惜的，由於\\n[5]沒有在自己身體的改造上多加了解，"]},{"code":401,"indent":1,"parameters":["她身上的力量也沒有被激發。"]},{"code":250,"indent":1,"parameters":[{"name":"Book1","volume":90,"pitch":100,"pan":0}]},{"code":101,"indent":1,"parameters":["03.SH1",2,1,2,""]},{"code":401,"indent":1,"parameters":["於歐提克之戰後的兩年，她的再生能力不再受控，"]},{"code":401,"indent":1,"parameters":["最終反而殺死了她這位宿主。"]},{"code":119,"indent":1,"parameters":["d"]},{"code":0,"indent":1,"parameters":[]},{"code":412,"indent":0,"parameters":[]},{"code":111,"indent":0,"parameters":[0,61,1]},{"code":108,"indent":1,"parameters":["如果未能了解到關於自身身為沼澤人的真相，"]},{"code":408,"indent":1,"parameters":["將懵懵懂懂的因為自身身上發生的各種感到痛苦鬱鬱寡歡的過完一生。"]},{"code":250,"indent":1,"parameters":[{"name":"Book1","volume":90,"pitch":100,"pan":0}]},{"code":101,"indent":1,"parameters":["03.SH1",2,1,2,""]},{"code":401,"indent":1,"parameters":["\\n[5]直到最後都不願面對有關自身的真相，"]},{"code":401,"indent":1,"parameters":["她隱約知道那是什麼，但始終無法鼓起勇氣去讓自己知道。"]},{"code":118,"indent":1,"parameters":["2"]},{"code":250,"indent":1,"parameters":[{"name":"Book1","volume":90,"pitch":100,"pan":0}]},{"code":101,"indent":1,"parameters":["03.SH1",2,1,2,""]},{"code":401,"indent":1,"parameters":["最終她在擔驚訝受怕之下，鬱鬱寡歡的過完了她的一生。"]},{"code":119,"indent":1,"parameters":["d"]},{"code":0,"indent":1,"parameters":[]},{"code":412,"indent":0,"parameters":[]},{"code":111,"indent":0,"parameters":[0,61,0]},{"code":122,"indent":1,"parameters":[6,6,0,0,0]},{"code":108,"indent":1,"parameters":["如果知道自身沼澤人的真相，"]},{"code":408,"indent":1,"parameters":["但沒能和奈爾梅絲談出個結果的同時也沒能在自身的幻象空間作完最後的納勒迦系列支線任務，"]},{"code":408,"indent":1,"parameters":["就會在有強烈迷失感的情況下渾渾噩噩過完一生。"]},{"code":111,"indent":1,"parameters":[0,62,0]},{"code":122,"indent":2,"parameters":[6,6,0,0,1]},{"code":0,"indent":2,"parameters":[]},{"code":412,"indent":1,"parameters":[]},{"code":111,"indent":1,"parameters":[0,63,0]},{"code":122,"indent":2,"parameters":[6,6,0,0,1]},{"code":0,"indent":2,"parameters":[]},{"code":412,"indent":1,"parameters":[]},{"code":111,"indent":1,"parameters":[1,39,0,100,1]},{"code":122,"indent":2,"parameters":[6,6,0,0,1]},{"code":0,"indent":2,"parameters":[]},{"code":412,"indent":1,"parameters":[]},{"code":111,"indent":1,"parameters":[1,6,0,0,0]},{"code":250,"indent":2,"parameters":[{"name":"Book1","volume":90,"pitch":100,"pan":0}]},{"code":101,"indent":2,"parameters":["03.SH1",2,1,2,""]},{"code":401,"indent":2,"parameters":["儘管知曉了自己身分的真相，"]},{"code":401,"indent":2,"parameters":["但她始終沒能下定決心面對自己的身分。"]},{"code":111,"indent":2,"parameters":[0,39,1]},{"code":250,"indent":3,"parameters":[{"name":"Book1","volume":90,"pitch":100,"pan":0}]},{"code":101,"indent":3,"parameters":["03.SH1",2,1,2,""]},{"code":401,"indent":3,"parameters":["\\n[12]試圖陪伴這樣的她好一段時間，"]},{"code":401,"indent":3,"parameters":["但\\n[5]始終沒能解開自身的心結，反而更加依賴她的導師。"]},{"code":250,"indent":3,"parameters":[{"name":"Book1","volume":90,"pitch":100,"pan":0}]},{"code":101,"indent":3,"parameters":["03.SH1",2,1,2,""]},{"code":401,"indent":3,"parameters":["\\n[5]的行為逐漸使\\n[12]反感，"]},{"code":401,"indent":3,"parameters":["在某一日，他了無聲息地拋下了\\n[5]。"]},{"code":0,"indent":3,"parameters":[]},{"code":412,"indent":2,"parameters":[]},{"code":119,"indent":2,"parameters":["2"]},{"code":0,"indent":2,"parameters":[]},{"code":412,"indent":1,"parameters":[]},{"code":0,"indent":1,"parameters":[]},{"code":412,"indent":0,"parameters":[]},{"code":108,"indent":0,"parameters":["※好結局的部分"]},{"code":111,"indent":0,"parameters":[1,39,0,100,1]},{"code":250,"indent":1,"parameters":[{"name":"Book1","volume":90,"pitch":100,"pan":0}]},{"code":101,"indent":1,"parameters":["03.SH1",3,1,2,""]},{"code":401,"indent":1,"parameters":["在聖劍的考驗之後，"]},{"code":401,"indent":1,"parameters":["\\n[5]終於明白自己想要的是什麼。"]},{"code":250,"indent":1,"parameters":[{"name":"Book1","volume":90,"pitch":100,"pan":0}]},{"code":101,"indent":1,"parameters":["03.SH1",3,1,2,""]},{"code":401,"indent":1,"parameters":["她不再依賴她的兩位導師，"]},{"code":401,"indent":1,"parameters":["而是走出了一條屬於自己的道路。"]},{"code":243,"indent":1,"parameters":[]},{"code":111,"indent":1,"parameters":[0,64,0]},{"code":108,"indent":2,"parameters":["拔起聖劍，以術士的身分持續奮戰"]},{"code":250,"indent":2,"parameters":[{"name":"Book1","volume":90,"pitch":100,"pan":0}]},{"code":232,"indent":2,"parameters":[99,0,0,0,510,120,100,100,0,0,30,true,0]},{"code":221,"indent":2,"parameters":[]},{"code":117,"indent":2,"parameters":[8]},{"code":129,"indent":2,"parameters":[11,1,true]},{"code":129,"indent":2,"parameters":[16,0,true]},{"code":205,"indent":2,"parameters":[-1,{"list":[{"code":19,"indent":null},{"code":40,"indent":null},{"code":38,"indent":null},{"code":0}],"repeat":false,"skippable":false,"wait":true}]},{"code":505,"indent":2,"parameters":[{"code":19,"indent":null}]},{"code":505,"indent":2,"parameters":[{"code":40,"indent":null}]},{"code":505,"indent":2,"parameters":[{"code":38,"indent":null}]},{"code":201,"indent":2,"parameters":[0,166,20,23,8,0]},{"code":223,"indent":2,"parameters":[[0,0,0,0],1,true]},{"code":222,"indent":2,"parameters":[]},{"code":205,"indent":2,"parameters":[-1,{"list":[{"code":4,"indent":null},{"code":0}],"repeat":false,"skippable":false,"wait":true}]},{"code":505,"indent":2,"parameters":[{"code":4,"indent":null}]},{"code":213,"indent":2,"parameters":[-1,7,true]},{"code":101,"indent":2,"parameters":["29.ENDING_ZHAO",6,0,2,"\\n[16]"]},{"code":401,"indent":2,"parameters":["——真遺憾我沒有好消息給Karcist聽。"]},{"code":213,"indent":2,"parameters":[-1,7,true]},{"code":101,"indent":2,"parameters":["29.ENDING_ZHAO",6,0,2,"\\n[16]"]},{"code":401,"indent":2,"parameters":["希望她對此不要感到太難過。"]},{"code":0,"indent":2,"parameters":[]},{"code":411,"indent":1,"parameters":[]},{"code":108,"indent":2,"parameters":["沒有拔起聖劍，以蛇之手的身分過完一生"]},{"code":243,"indent":2,"parameters":[]},{"code":250,"indent":2,"parameters":[{"name":"Book1","volume":90,"pitch":100,"pan":0}]},{"code":232,"indent":2,"parameters":[99,0,0,0,510,120,100,100,0,0,30,true,0]},{"code":221,"indent":2,"parameters":[]},{"code":117,"indent":2,"parameters":[8]},{"code":129,"indent":2,"parameters":[11,1,true]},{"code":129,"indent":2,"parameters":[5,0,false]},{"code":322,"indent":2,"parameters":[5,"20.Ending_ZHAO",0,"29.ENDING_ZHAO",0,"SH01_ZHAO_ZHEN"]},{"code":223,"indent":2,"parameters":[[0,0,0,0],1,true]},{"code":201,"indent":2,"parameters":[0,165,8,14,8,0]},{"code":205,"indent":2,"parameters":[-1,{"list":[{"code":37,"indent":null},{"code":4,"indent":null},{"code":4,"indent":null},{"code":4,"indent":null},{"code":0}],"repeat":false,"skippable":false,"wait":true}]},{"code":505,"indent":2,"parameters":[{"code":37,"indent":null}]},{"code":505,"indent":2,"parameters":[{"code":4,"indent":null}]},{"code":505,"indent":2,"parameters":[{"code":4,"indent":null}]},{"code":505,"indent":2,"parameters":[{"code":4,"indent":null}]},{"code":222,"indent":2,"parameters":[]},{"code":0,"indent":2,"parameters":[]},{"code":412,"indent":1,"parameters":[]},{"code":115,"indent":1,"parameters":[]},{"code":0,"indent":1,"parameters":[]},{"code":412,"indent":0,"parameters":[]},{"code":108,"indent":0,"parameters":["知道真相又下定決心或蹭蹭奈爾，但沒有完成聖劍聖物"]},{"code":408,"indent":0,"parameters":["則會作為普通人過完一生"]},{"code":111,"indent":0,"parameters":[1,39,0,100,4]},{"code":122,"indent":1,"parameters":[6,6,0,0,0]},{"code":111,"indent":1,"parameters":[0,62,0]},{"code":122,"indent":2,"parameters":[6,6,0,0,1]},{"code":0,"indent":2,"parameters":[]},{"code":412,"indent":1,"parameters":[]},{"code":111,"indent":1,"parameters":[0,63,0]},{"code":122,"indent":2,"parameters":[6,6,0,0,1]},{"code":0,"indent":2,"parameters":[]},{"code":412,"indent":1,"parameters":[]},{"code":111,"indent":1,"parameters":[1,6,0,1,0]},{"code":250,"indent":2,"parameters":[{"name":"Book1","volume":90,"pitch":100,"pan":0}]},{"code":101,"indent":2,"parameters":["03.SH1",0,1,2,""]},{"code":401,"indent":2,"parameters":["終究不論是蛇之手還是納勒迦，對\\n[5]來說都是不自由的，"]},{"code":401,"indent":2,"parameters":["於是她選擇以一位普通再生者的身分過完了她的人生。"]},{"code":250,"indent":2,"parameters":[{"name":"Book1","volume":90,"pitch":100,"pan":0}]},{"code":101,"indent":2,"parameters":["06.SH3",3,1,2,""]},{"code":401,"indent":2,"parameters":["當然，"]},{"code":401,"indent":2,"parameters":["在那之前她還得回頭補完跟著蛇之手們到處跑的而落下的學業，"]},{"code":401,"indent":2,"parameters":["她花了五年拿到了鹿學院的文憑後持續進修，"]},{"code":401,"indent":2,"parameters":["最終在當地成為了一位小有名氣的學者。"]},{"code":122,"indent":2,"parameters":[53,53,0,0,0]},{"code":0,"indent":2,"parameters":[]},{"code":412,"indent":1,"parameters":[]},{"code":0,"indent":1,"parameters":[]},{"code":412,"indent":0,"parameters":[]},{"code":118,"indent":0,"parameters":["d"]},{"code":122,"indent":0,"parameters":[53,53,0,0,0]},{"code":232,"indent":0,"parameters":[99,0,0,0,510,120,100,100,0,0,30,true,0]},{"code":357,"indent":0,"parameters":["VisuMZ_0_CoreEngine","PictureEraseAll","Picture: Erase All",{}]},{"code":221,"indent":0,"parameters":[]},{"code":223,"indent":0,"parameters":[[0,0,0,0],1,false]},{"code":201,"indent":0,"parameters":[0,167,8,6,0,0]},{"code":222,"indent":0,"parameters":[]},{"code":115,"indent":0,"parameters":[]},{"code":0,"indent":0,"parameters":[]}],"moveFrequency":3,"moveRoute":{"list":[{"code":0,"parameters":[]}],"repeat":true,"skippable":false,"wait":false},"moveSpeed":3,"moveType":0,"priorityType":0,"stepAnime":false,"through":false,"trigger":3,"walkAnime":true},{"conditions":{"actorId":1,"actorValid":false,"itemId":1,"itemValid":false,"selfSwitchCh":"A","selfSwitchValid":false,"switch1Id":72,"switch1Valid":true,"switch2Id":1,"switch2Valid":false,"variableId":53,"variableValid":true,"variableValue":0},"directionFix":false,"image":{"characterIndex":0,"characterName":"","direction":2,"pattern":0,"tileId":0},"list":[{"code":284,"indent":0,"parameters":["Space",true,false,5,0]},{"code":241,"indent":0,"parameters":[{"name":"287_night_wind","volume":90,"pitch":100,"pan":0}]},{"code":281,"indent":0,"parameters":[1]},{"code":122,"indent":0,"parameters":[53,53,0,0,0]},{"code":357,"indent":0,"parameters":["VisuMZ_1_EventsMoveCore","EventLabelVisible","Event Label: Visible",{"Visibility:str":"Hidden"}]},{"code":657,"indent":0,"parameters":["Visibility = Hidden"]},{"code":222,"indent":0,"parameters":[]},{"code":122,"indent":0,"parameters":[11,11,0,0,0]},{"code":122,"indent":0,"parameters":[12,12,0,0,-40]},{"code":117,"indent":0,"parameters":[13]},{"code":250,"indent":0,"parameters":[{"name":"Autodoor","volume":90,"pitch":100,"pan":0}]},{"code":231,"indent":0,"parameters":[99,"GOC-Logo",1,1,11,12,100,100,0,0]},{"code":234,"indent":0,"parameters":[99,[0,0,0,255],1,false]},{"code":232,"indent":0,"parameters":[99,0,1,1,11,12,100,100,255,0,20,true,0]},{"code":230,"indent":0,"parameters":[60]},{"code":101,"indent":0,"parameters":["",0,1,1,""]},{"code":401,"indent":0,"parameters":["<center>自由與秩序長久以來不斷相爭，有時是秩序勝利、有時是自由佔上風，"]},{"code":401,"indent":0,"parameters":["而這一次，GOC最終獲得了勝利，帷幕被維持住，"]},{"code":401,"indent":0,"parameters":["這群秩序維護者們再一次守護了現有的世界。"]},{"code":108,"indent":0,"parameters":["※計算和平與否，GOC比較難達成和平"]},{"code":111,"indent":0,"parameters":[1,36,0,27,1]},{"code":121,"indent":1,"parameters":[86,86,1]},{"code":0,"indent":1,"parameters":[]},{"code":411,"indent":0,"parameters":[]},{"code":121,"indent":1,"parameters":[86,86,0]},{"code":0,"indent":1,"parameters":[]},{"code":412,"indent":0,"parameters":[]},{"code":108,"indent":0,"parameters":["※結局1"]},{"code":408,"indent":0,"parameters":["世界的狀況"]},{"code":122,"indent":0,"parameters":[53,53,0,0,1]},{"code":122,"indent":0,"parameters":[11,11,0,0,0]},{"code":122,"indent":0,"parameters":[12,12,0,0,0]},{"code":117,"indent":0,"parameters":[13]},{"code":250,"indent":0,"parameters":[{"name":"Book1","volume":90,"pitch":100,"pan":0}]},{"code":231,"indent":0,"parameters":[99,"ending/ENDIND1",1,1,11,12,100,100,0,0]},{"code":234,"indent":0,"parameters":[99,[0,0,0,255],1,false]},{"code":232,"indent":0,"parameters":[99,0,1,1,11,12,100,100,255,0,20,true,0]},{"code":111,"indent":0,"parameters":[0,86,0]},{"code":101,"indent":1,"parameters":["",0,1,2,""]},{"code":401,"indent":1,"parameters":["<center>在諸多GOC成員的努力下，帷幕仍被維持，"]},{"code":401,"indent":1,"parameters":["儘管似乎越來越不穩固，GOC在其間犯下的各種戰爭罪行使越來越多人支持蛇之手的說法，"]},{"code":401,"indent":1,"parameters":["各式反抗組織數量爆炸性的成長不斷，GOC的傷亡也越來越多。"]},{"code":250,"indent":1,"parameters":[{"name":"Book1","volume":90,"pitch":100,"pan":0}]},{"code":101,"indent":1,"parameters":["",0,1,2,""]},{"code":401,"indent":1,"parameters":["<center>由於強烈的反抗，被視為怪物的人們仍舊被視作怪物，"]},{"code":401,"indent":1,"parameters":["GOC只得使用更加粗暴的手段去消滅反對者，"]},{"code":401,"indent":1,"parameters":["其惡性循環的結果，就是GOC的對超人類的排斥越發越強烈。"]},{"code":250,"indent":1,"parameters":[{"name":"Book1","volume":90,"pitch":100,"pan":0}]},{"code":101,"indent":1,"parameters":["",0,1,2,""]},{"code":401,"indent":1,"parameters":["<center>最終佔上風的GOC們打造了一個比戰前更加優待基準人類，"]},{"code":401,"indent":1,"parameters":["迫害超人類與非人類的瘋狂世界，而這類狀況仍在不斷惡化當中。"]},{"code":0,"indent":1,"parameters":[]},{"code":411,"indent":0,"parameters":[]},{"code":101,"indent":1,"parameters":["",0,1,2,""]},{"code":401,"indent":1,"parameters":["<center>在諸多GOC成員的努力下，帷幕仍被維持，"]},{"code":401,"indent":1,"parameters":["GOC在征戰中表現的克制讓他們在一定程度上受到了肯定，"]},{"code":401,"indent":1,"parameters":["甚至破天荒的僅判除某些「罪刑較輕的蛇之手」數年的刑期。"]},{"code":250,"indent":1,"parameters":[{"name":"Book1","volume":90,"pitch":100,"pan":0}]},{"code":101,"indent":1,"parameters":["",0,1,2,""]},{"code":401,"indent":1,"parameters":["<center>也因帷幕仍然維持，"]},{"code":401,"indent":1,"parameters":["帷幕外的人們對世界上發生了這麼大的事情渾然不覺，"]},{"code":401,"indent":1,"parameters":["但對GOC內部更加懾人的事情發生了。"]},{"code":250,"indent":1,"parameters":[{"name":"Book1","volume":90,"pitch":100,"pan":0}]},{"code":101,"indent":1,"parameters":["",0,1,2,""]},{"code":401,"indent":1,"parameters":["<center>在D.C. AL Fine議長的領導下，GOC開始改革，"]},{"code":401,"indent":1,"parameters":["儘管仍有相當多的問題，但聯盟的確正在朝對異常人類更加友善的方向走去，"]},{"code":401,"indent":1,"parameters":["這也使得GOC內部的保守派意圖罷免這位萬年議長，所幸他們都失敗了。"]},{"code":0,"indent":1,"parameters":[]},{"code":412,"indent":0,"parameters":[]},{"code":250,"indent":0,"parameters":[{"name":"Book1","volume":90,"pitch":100,"pan":0}]},{"code":101,"indent":0,"parameters":["",0,1,2,""]},{"code":401,"indent":0,"parameters":["<center>然而由於蛇之手非正式組織的性質，他們是不可能真正被消滅的，"]},{"code":401,"indent":0,"parameters":["這些超人類民兵們在歐提克之戰失敗後，回到過去他們對GOC的零星騷擾活動，"]},{"code":401,"indent":0,"parameters":["仍然對GOC懷抱不信任與敵意，當中的激進份子成為了GOC所掌控都市的安全隱患。"]},{"code":108,"indent":0,"parameters":["※判斷歐提克的狀況"]},{"code":122,"indent":0,"parameters":[53,53,0,0,2]},{"code":122,"indent":0,"parameters":[11,11,0,0,0]},{"code":122,"indent":0,"parameters":[12,12,0,0,0]},{"code":117,"indent":0,"parameters":[13]},{"code":231,"indent":0,"parameters":[99,"ending/Ending2_Eutec",1,1,11,12,100,100,0,0]},{"code":234,"indent":0,"parameters":[99,[0,0,0,255],1,false]},{"code":232,"indent":0,"parameters":[99,0,1,1,11,12,100,100,255,0,20,true,0]},{"code":250,"indent":0,"parameters":[{"name":"Book1","volume":90,"pitch":100,"pan":0}]},{"code":101,"indent":0,"parameters":["",0,1,2,""]},{"code":401,"indent":0,"parameters":["歐提克被守住了，蛇之手與他們召募的聯軍死傷慘重退出了歐提克城，"]},{"code":401,"indent":0,"parameters":["GOC再一次向帷幕內的世人們證明了他們作為人類守夜人的強悍所在。"]},{"code":108,"indent":0,"parameters":["※通常情況"]},{"code":250,"indent":0,"parameters":[{"name":"Book1","volume":90,"pitch":100,"pan":0}]},{"code":111,"indent":0,"parameters":[0,86,0]},{"code":101,"indent":1,"parameters":["",0,1,2,""]},{"code":401,"indent":1,"parameters":["戰爭帶來的災害重建還需要很多時間，然而即便他們打退了蛇之手，"]},{"code":401,"indent":1,"parameters":["其他新生的反抗組織成為了歐提克的新困擾，"]},{"code":401,"indent":1,"parameters":["而他們當中不乏遠比蛇之手更加激進殘忍的人們，為歐提克的平民帶來嚴重損害。"]},{"code":111,"indent":1,"parameters":[0,60,0]},{"code":250,"indent":2,"parameters":[{"name":"Book1","volume":90,"pitch":100,"pan":0}]},{"code":101,"indent":2,"parameters":["",0,1,2,""]},{"code":401,"indent":2,"parameters":["更糟的是，由於D.C. Al Fine曾下令舉辦對超人類犧牲者們的追思會，"]},{"code":401,"indent":2,"parameters":["這使得超人類的同情者數量更多，反抗組織的人力源源不絕。"]},{"code":0,"indent":2,"parameters":[]},{"code":412,"indent":1,"parameters":[]},{"code":0,"indent":1,"parameters":[]},{"code":411,"indent":0,"parameters":[]},{"code":108,"indent":1,"parameters":["※一旦對米茲蠟希復仇，安東尼將無法成為總指揮官"]},{"code":111,"indent":1,"parameters":[1,38,0,1,1]},{"code":101,"indent":2,"parameters":["",0,1,2,""]},{"code":401,"indent":2,"parameters":["戰爭帶來的災害重建還需要很多時間，然而即便他們打退了蛇之手，"]},{"code":401,"indent":2,"parameters":["也還有很多工作要做。"]},{"code":0,"indent":2,"parameters":[]},{"code":411,"indent":1,"parameters":[]},{"code":101,"indent":2,"parameters":["",0,1,2,""]},{"code":401,"indent":2,"parameters":["戰爭帶來的災害重建還需要很多時間，然而即便他們打退了蛇之手，"]},{"code":401,"indent":2,"parameters":["也還有很多工作要做，新任的歐提克總指揮官是由D.C. Al Fine親自安排上任的，"]},{"code":401,"indent":2,"parameters":["他似乎更加善待超人類，這也讓歐提克內部矛盾降低了不少。"]},{"code":0,"indent":2,"parameters":[]},{"code":412,"indent":1,"parameters":[]},{"code":111,"indent":1,"parameters":[0,60,0]},{"code":250,"indent":2,"parameters":[{"name":"Book1","volume":90,"pitch":100,"pan":0}]},{"code":101,"indent":2,"parameters":["",0,1,2,""]},{"code":401,"indent":2,"parameters":["由於D.C. Al Fine曾下令舉辦對超人類犧牲者們的追思會，"]},{"code":401,"indent":2,"parameters":["儘管過往的歐提克只接納藍型，輔以新任總指揮官的協助下，"]},{"code":401,"indent":2,"parameters":["現在他們變得更加能接納此外的超人類了。"]},{"code":0,"indent":2,"parameters":[]},{"code":412,"indent":1,"parameters":[]},{"code":0,"indent":1,"parameters":[]},{"code":412,"indent":0,"parameters":[]},{"code":108,"indent":0,"parameters":["※結局2"]},{"code":408,"indent":0,"parameters":["三波特蘭的狀況"]},{"code":122,"indent":0,"parameters":[53,53,0,0,3]},{"code":122,"indent":0,"parameters":[11,11,0,0,0]},{"code":122,"indent":0,"parameters":[12,12,0,0,0]},{"code":117,"indent":0,"parameters":[13]},{"code":250,"indent":0,"parameters":[{"name":"Book1","volume":90,"pitch":100,"pan":0}]},{"code":231,"indent":0,"parameters":[99,"ending/Ending2_TPLD",1,1,11,12,100,100,0,0]},{"code":234,"indent":0,"parameters":[99,[0,0,0,255],1,false]},{"code":232,"indent":0,"parameters":[99,0,1,1,11,12,100,100,255,0,20,true,0]},{"code":108,"indent":0,"parameters":["※判斷三波特蘭的狀況"]},{"code":101,"indent":0,"parameters":["",0,1,2,""]},{"code":401,"indent":0,"parameters":["在歐提克之戰後，三波特蘭旋即也被捲土重來的GOC攻下，"]},{"code":401,"indent":0,"parameters":["GOC終究將這個北美最大異常飛地納入囊中，儘管有不少勢力對GOC不滿，卻也僅只能在口頭上表達，"]},{"code":401,"indent":0,"parameters":["因為掌握了三波特蘭的GOC也變得比以前更加強大、更難以招惹了。"]},{"code":111,"indent":0,"parameters":[0,86,0]},{"code":250,"indent":1,"parameters":[{"name":"Book1","volume":90,"pitch":100,"pan":0}]},{"code":101,"indent":1,"parameters":["",0,1,2,""]},{"code":401,"indent":1,"parameters":["仍然沒有變化的GOC在進入城市後就將70%的人口系統性屠殺，"]},{"code":401,"indent":1,"parameters":["所有超人類與非人類都被當成威脅消滅，就如同貝恩德‧泰勒先前所計畫的一樣。"]},{"code":111,"indent":1,"parameters":[0,89,1]},{"code":250,"indent":2,"parameters":[{"name":"Book1","volume":90,"pitch":100,"pan":0}]},{"code":101,"indent":2,"parameters":["",0,1,2,""]},{"code":401,"indent":2,"parameters":["那一天，泰勒自豪的說：「諸位，我們已成功將三波特蘭正常化！」"]},{"code":0,"indent":2,"parameters":[]},{"code":412,"indent":1,"parameters":[]},{"code":250,"indent":1,"parameters":[{"name":"Book1","volume":90,"pitch":100,"pan":0}]},{"code":101,"indent":1,"parameters":["",0,1,2,""]},{"code":401,"indent":1,"parameters":["而毫不意外的，這一作為獲得了聯盟內部諸多掌聲。"]},{"code":0,"indent":1,"parameters":[]},{"code":411,"indent":0,"parameters":[]},{"code":111,"indent":1,"parameters":[0,78,0]},{"code":101,"indent":2,"parameters":["",0,1,2,""]},{"code":401,"indent":2,"parameters":["在三波特蘭兩次大戰後，三波特蘭受到了極其嚴重的損害，"]},{"code":401,"indent":2,"parameters":["不論是人力與財產都受到了致命的打擊。"]},{"code":250,"indent":2,"parameters":[{"name":"Book1","volume":90,"pitch":100,"pan":0}]},{"code":101,"indent":2,"parameters":["",0,1,2,""]},{"code":401,"indent":2,"parameters":["居民對這個曾經的魔幻土地感到失望，"]},{"code":401,"indent":2,"parameters":["GOC新成立的傀儡議會也無法拿出適當的解決方案，"]},{"code":401,"indent":2,"parameters":["於是人們逐漸向外移民，三波特蘭恐怕再也無法回歸過往的輝煌。"]},{"code":0,"indent":2,"parameters":[]},{"code":411,"indent":1,"parameters":[]},{"code":250,"indent":2,"parameters":[{"name":"Book1","volume":90,"pitch":100,"pan":0}]},{"code":101,"indent":2,"parameters":["",0,1,2,""]},{"code":401,"indent":2,"parameters":["在佔領三波特蘭後，GOC開始著手建設與改革三波特蘭的體制，"]},{"code":401,"indent":2,"parameters":["原有的市長只能請他「讓位」，並成立新的傀儡市議會，儘管反抗聲音仍然不小，"]},{"code":401,"indent":2,"parameters":["但讓人閉嘴的手段GOC要多少有多少。"]},{"code":250,"indent":2,"parameters":[{"name":"Book1","volume":90,"pitch":100,"pan":0}]},{"code":101,"indent":2,"parameters":["",0,1,2,""]},{"code":401,"indent":2,"parameters":["然而習慣了過往高稅制高福利的社會制度，"]},{"code":401,"indent":2,"parameters":["居民的工作意願普遍遠差於歐提克等GOC控制的那些城市，對GOC不滿的人越來越多，"]},{"code":401,"indent":2,"parameters":["這些人在GOC來了之後更有理由與動機選擇躺平也不願為GOC工作，合理且正義的成為社會蛀蟲，"]},{"code":401,"indent":2,"parameters":["比起高調的反抗，沉默的反抗或許才是GOC更大的挑戰。"]},{"code":0,"indent":2,"parameters":[]},{"code":412,"indent":1,"parameters":[]},{"code":0,"indent":1,"parameters":[]},{"code":412,"indent":0,"parameters":[]},{"code":108,"indent":0,"parameters":["※伊瓦迪村的狀況"]},{"code":122,"indent":0,"parameters":[53,53,0,0,3]},{"code":122,"indent":0,"parameters":[11,11,0,0,0]},{"code":122,"indent":0,"parameters":[12,12,0,0,0]},{"code":117,"indent":0,"parameters":[13]},{"code":231,"indent":0,"parameters":[99,"ending/Ending3_Ivady",1,1,11,12,100,100,0,0]},{"code":234,"indent":0,"parameters":[99,[0,0,0,255],1,false]},{"code":232,"indent":0,"parameters":[99,0,1,1,11,12,100,100,255,0,20,true,0]},{"code":250,"indent":0,"parameters":[{"name":"Book1","volume":90,"pitch":100,"pan":0}]},{"code":108,"indent":0,"parameters":["※判斷伊瓦迪村的狀況"]},{"code":108,"indent":0,"parameters":["※金莉任務有無作完"]},{"code":101,"indent":0,"parameters":["",0,1,2,""]},{"code":401,"indent":0,"parameters":["伊瓦迪村在遭受GOC襲擊後，幾乎所有村中孩童死亡，聖樹也被摧毀，"]},{"code":401,"indent":0,"parameters":["村中原本的希望\\n[14]也死於GOC槍下，原本和瑪納慈善基金會合作的他們再也沒有本錢那麼做了。"]},{"code":250,"indent":0,"parameters":[{"name":"Book1","volume":90,"pitch":100,"pan":0}]},{"code":101,"indent":0,"parameters":["",0,1,2,""]},{"code":401,"indent":0,"parameters":["現在村民們都正接受基金會的保護，就算伊瓦迪村可能還有什麼希望，"]},{"code":401,"indent":0,"parameters":["在GOC已經定性伊瓦迪村是可能威脅的當下，過往的村落除了任其荒廢以外別無他法，"]},{"code":401,"indent":0,"parameters":["可以說只要GOC掌控異常世界的一天，伊瓦迪村就不可能有重建的一天。"]},{"code":108,"indent":0,"parameters":["※哈柏希爾的狀況"]},{"code":122,"indent":0,"parameters":[53,53,0,0,5]},{"code":122,"indent":0,"parameters":[11,11,0,0,0]},{"code":122,"indent":0,"parameters":[12,12,0,0,0]},{"code":117,"indent":0,"parameters":[13]},{"code":231,"indent":0,"parameters":[99,"ending/Ending4_HyBrasil",1,1,11,12,100,100,0,0]},{"code":234,"indent":0,"parameters":[99,[0,0,0,255],1,false]},{"code":232,"indent":0,"parameters":[99,0,1,1,11,12,100,100,255,0,20,true,0]},{"code":250,"indent":0,"parameters":[{"name":"Book1","volume":90,"pitch":100,"pan":0}]},{"code":111,"indent":0,"parameters":[0,56,1]},{"code":101,"indent":1,"parameters":["13.others4",2,1,2,""]},{"code":401,"indent":1,"parameters":["因為\\n[8]的手下留情，魯格四世活了下來，"]},{"code":401,"indent":1,"parameters":["這個野心家不會屈服於牢獄之災，在蛇之手與GOC都離開島上後，"]},{"code":401,"indent":1,"parameters":["他抓準時機又來了一次裡應外合，成功發動了政變。"]},{"code":111,"indent":1,"parameters":[0,86,1]},{"code":122,"indent":2,"parameters":[6,6,0,4,"\"這一提案被採納了，雙邊的關係開始修復。\""]},{"code":0,"indent":2,"parameters":[]},{"code":411,"indent":1,"parameters":[]},{"code":122,"indent":2,"parameters":[6,6,0,4,"\"然而在GOC要求他交出所有島上的綠型以處決後，事情有了變化。\""]},{"code":0,"indent":2,"parameters":[]},{"code":412,"indent":1,"parameters":[]},{"code":101,"indent":1,"parameters":["13.others4",2,1,2,""]},{"code":401,"indent":1,"parameters":["德爾貝斯成為了階下囚後，魯格很快的找上了GOC要求再次結盟，"]},{"code":401,"indent":1,"parameters":["\\V[6]"]},{"code":250,"indent":1,"parameters":[{"name":"Book1","volume":90,"pitch":100,"pan":0}]},{"code":111,"indent":1,"parameters":[0,86,1]},{"code":101,"indent":2,"parameters":["13.others4",2,1,2,""]},{"code":401,"indent":2,"parameters":["108議會在一段時間後變作了109議會，"]},{"code":401,"indent":2,"parameters":["圖哈德達南正式成為了第109個成員組織，顯現了GOC對表現對異常改變態度的決心。"]},{"code":111,"indent":2,"parameters":[1,28,0,6,1]},{"code":111,"indent":3,"parameters":[0,47,1]},{"code":250,"indent":4,"parameters":[{"name":"Book1","volume":90,"pitch":100,"pan":0}]},{"code":101,"indent":4,"parameters":["13.others4",2,1,2,""]},{"code":401,"indent":4,"parameters":["作為友好的證明，若干年後魯格王子親自到洛克菲勒將軍在三波特蘭的墓獻花，"]},{"code":401,"indent":4,"parameters":["據說洛克菲勒生前一直努力在進行一系列活動：消彌三波特蘭希神與人類居民之間的矛盾"]},{"code":401,"indent":4,"parameters":["，也消彌對超人類的仇恨，他的獻身最終使得某些哈伯希爾的希神也原諒了他。"]},{"code":0,"indent":4,"parameters":[]},{"code":412,"indent":3,"parameters":[]},{"code":0,"indent":3,"parameters":[]},{"code":412,"indent":2,"parameters":[]},{"code":250,"indent":2,"parameters":[{"name":"Book1","volume":90,"pitch":100,"pan":0}]},{"code":101,"indent":2,"parameters":["13.others4",2,1,2,""]},{"code":401,"indent":2,"parameters":["在GOC的資助之下，哈伯希爾飛速的成長，到了魯格想都不敢想的地步，"]},{"code":401,"indent":2,"parameters":["然而外來的文化與資源與本國文化之間的矛盾也帶來衝突，"]},{"code":401,"indent":2,"parameters":["魯格也正在逐漸失去對國家的掌握力，這是魯格必須要擔心的新問題。"]},{"code":0,"indent":2,"parameters":[]},{"code":411,"indent":1,"parameters":[]},{"code":101,"indent":2,"parameters":["13.others4",2,1,2,""]},{"code":401,"indent":2,"parameters":["這一舉動顯然嚴重冒犯了魯格，"]},{"code":401,"indent":2,"parameters":["魯格當著眾人的面砍下來GOC使者的頭顱，並下令殺光所有GOC的來使，"]},{"code":401,"indent":2,"parameters":["仗著七年才能來往一次的迷霧，GOC暫時也拿他們沒辦法。"]},{"code":250,"indent":2,"parameters":[{"name":"Book1","volume":90,"pitch":100,"pan":0}]},{"code":101,"indent":2,"parameters":["13.others4",2,1,2,""]},{"code":401,"indent":2,"parameters":["並且，毫不意外的他倒向了蛇之手那一方，並在蛇之手的協助下艱難的進行改革，"]},{"code":401,"indent":2,"parameters":["聽上去現在GOC多了一整個異常國度的敵人，但反正他們的規模對GOC來說無足輕重，"]},{"code":401,"indent":2,"parameters":["GOC沒有太在意哈伯希爾，誰會害怕一個只剩數千人的國度呢？"]},{"code":250,"indent":2,"parameters":[{"name":"Book1","volume":90,"pitch":100,"pan":0}]},{"code":101,"indent":2,"parameters":["13.others4",2,1,2,""]},{"code":401,"indent":2,"parameters":["但讓GOC跌破眼鏡的是，在魯格高明的外交手腕下，"]},{"code":401,"indent":2,"parameters":["願意資助哈伯希爾改革與幫助他們對抗GOC的人們比想像中多更多。"]},{"code":250,"indent":2,"parameters":[{"name":"Book1","volume":90,"pitch":100,"pan":0}]},{"code":101,"indent":2,"parameters":["13.others4",2,1,2,""]},{"code":401,"indent":2,"parameters":["許多傳統的陋習與不合時宜的法律也在他領導下接連被國民拋棄，"]},{"code":401,"indent":2,"parameters":["在經濟與軍事實力上比起過往的哈伯希爾完全不可同日而語，"]},{"code":401,"indent":2,"parameters":["哈伯希爾成為了一個真正強大的國家，一個GOC不容小覷的敵對國度。"]},{"code":0,"indent":2,"parameters":[]},{"code":412,"indent":1,"parameters":[]},{"code":0,"indent":1,"parameters":[]},{"code":411,"indent":0,"parameters":[]},{"code":250,"indent":1,"parameters":[{"name":"Book1","volume":90,"pitch":100,"pan":0}]},{"code":101,"indent":1,"parameters":["23.Others7",4,1,2,""]},{"code":401,"indent":1,"parameters":["哈伯希爾在魯格王子死後，國內再也無人能真正與國王德爾貝斯二世抗衡，"]},{"code":401,"indent":1,"parameters":["於是在國王的命令下，那個曾經招來大海怪的防護塔被再次建了起來，"]},{"code":401,"indent":1,"parameters":["整個哈伯希爾在經濟陷入頹勢的狀況下，等待著下個一千年的大災難。"]},{"code":250,"indent":1,"parameters":[{"name":"Book1","volume":90,"pitch":100,"pan":0}]},{"code":101,"indent":1,"parameters":["23.Others7",4,1,2,""]},{"code":401,"indent":1,"parameters":["儘管德爾貝斯二世明顯受到蛇之手的援助，"]},{"code":401,"indent":1,"parameters":["但GOC內部的智庫認為德爾貝斯政權對蛇之手來說比起資產更像是負債，"]},{"code":401,"indent":1,"parameters":["而他對GOC則毫無威脅，因此選擇放任不管。"]},{"code":250,"indent":1,"parameters":[{"name":"Book1","volume":90,"pitch":100,"pan":0}]},{"code":101,"indent":1,"parameters":["23.Others7",4,1,2,""]},{"code":401,"indent":1,"parameters":["不出GOC所料的是，蛇之手終究與德爾貝斯所領導的圖哈德達南政權發生了嚴重矛盾，"]},{"code":401,"indent":1,"parameters":["隨著國王被蛇之手刺殺，蛇之手也成為了島上的不受歡迎對象，"]},{"code":401,"indent":1,"parameters":["無人協助重建的圖哈德達南也更進一步走向滅亡。"]},{"code":0,"indent":1,"parameters":[]},{"code":412,"indent":0,"parameters":[]},{"code":108,"indent":0,"parameters":["※米茲蠟希的狀況"]},{"code":108,"indent":0,"parameters":["※判斷米茲蠟希否存活"]},{"code":408,"indent":0,"parameters":["０為存活"]},{"code":122,"indent":0,"parameters":[6,6,0,0,0]},{"code":111,"indent":0,"parameters":[0,46,0]},{"code":122,"indent":1,"parameters":[6,6,0,0,1]},{"code":0,"indent":1,"parameters":[]},{"code":412,"indent":0,"parameters":[]},{"code":111,"indent":0,"parameters":[1,38,0,5,1]},{"code":122,"indent":1,"parameters":[6,6,0,0,1]},{"code":0,"indent":1,"parameters":[]},{"code":412,"indent":0,"parameters":[]},{"code":250,"indent":0,"parameters":[{"name":"Book1","volume":90,"pitch":100,"pan":0}]},{"code":122,"indent":0,"parameters":[53,53,0,0,6]},{"code":122,"indent":0,"parameters":[11,11,0,0,0]},{"code":122,"indent":0,"parameters":[12,12,0,0,0]},{"code":117,"indent":0,"parameters":[13]},{"code":231,"indent":0,"parameters":[99,"ending/Ending5_Mizrahi",1,1,11,12,100,100,0,0]},{"code":234,"indent":0,"parameters":[99,[0,0,0,255],1,false]},{"code":232,"indent":0,"parameters":[99,0,1,1,11,12,100,100,255,0,20,true,0]},{"code":111,"indent":0,"parameters":[1,6,0,0,0]},{"code":101,"indent":1,"parameters":["18.Child_God_.Joshua",0,1,2,""]},{"code":401,"indent":1,"parameters":["儘管他的極端作為惹惱了數不清的勢力，"]},{"code":401,"indent":1,"parameters":["約書亞‧米茲蠟希這位幼稚之神還是存活了下來。"]},{"code":111,"indent":1,"parameters":[0,86,0]},{"code":250,"indent":2,"parameters":[{"name":"Book1","volume":90,"pitch":100,"pan":0}]},{"code":101,"indent":2,"parameters":["18.Child_God_.Joshua",0,1,2,""]},{"code":401,"indent":2,"parameters":["在數年給造成更多麻煩甚至傷亡後，"]},{"code":401,"indent":2,"parameters":["GOC仍然拿這位幼稚之神毫無辦法，"]},{"code":401,"indent":2,"parameters":["他也成為唯一一位被圖書館驅逐，卻也還是被認為是蛇巢領導的人。"]},{"code":250,"indent":2,"parameters":[{"name":"Book1","volume":90,"pitch":100,"pan":0}]},{"code":101,"indent":2,"parameters":["18.Child_God_.Joshua",0,1,2,""]},{"code":401,"indent":2,"parameters":["儘管許多蛇之手都不滿他的作為，"]},{"code":401,"indent":2,"parameters":["但不可否認的是許多人都需要這名幼稚之神的強大力量。"]},{"code":0,"indent":2,"parameters":[]},{"code":411,"indent":1,"parameters":[]},{"code":250,"indent":2,"parameters":[{"name":"Book1","volume":90,"pitch":100,"pan":0}]},{"code":101,"indent":2,"parameters":["18.Child_God_.Joshua",0,1,2,""]},{"code":401,"indent":2,"parameters":["在數年給造成更多麻煩甚至傷亡後，"]},{"code":401,"indent":2,"parameters":["GOC在付出慘痛代價後終於殺死了這個孤立無援的幼稚之神。"]},{"code":250,"indent":2,"parameters":[{"name":"Book1","volume":90,"pitch":100,"pan":0}]},{"code":101,"indent":2,"parameters":["18.Child_God_.Joshua",0,1,2,""]},{"code":401,"indent":2,"parameters":["米茲蠟希之所以會死，是因為他的作為惹怒了包含蛇之手在內的太多人，"]},{"code":401,"indent":2,"parameters":["這也使得他在蛇之手當中被孤立，甚至讓他被出賣給了GOC。"]},{"code":0,"indent":2,"parameters":[]},{"code":412,"indent":1,"parameters":[]},{"code":0,"indent":1,"parameters":[]},{"code":411,"indent":0,"parameters":[]},{"code":101,"indent":1,"parameters":["18.Child_God_.Joshua",0,1,2,""]},{"code":401,"indent":1,"parameters":["米茲蠟希這位強大的現實扭曲者死了，似乎在向其他現實扭曲者表明了一件事，"]},{"code":401,"indent":1,"parameters":["即便你有多麼強大的力量，惹惱了太多人之後還是會被幹掉的。"]},{"code":0,"indent":1,"parameters":[]},{"code":412,"indent":0,"parameters":[]},{"code":108,"indent":0,"parameters":["※SCP基金會的狀況"]},{"code":205,"indent":0,"parameters":[2,{"list":[{"code":41,"parameters":["04.others2",2],"indent":null},{"code":0}],"repeat":false,"skippable":false,"wait":true}]},{"code":505,"indent":0,"parameters":[{"code":41,"parameters":["04.others2",2],"indent":null}]},{"code":122,"indent":0,"parameters":[53,53,0,0,7]},{"code":122,"indent":0,"parameters":[11,11,0,0,0]},{"code":122,"indent":0,"parameters":[12,12,0,0,0]},{"code":117,"indent":0,"parameters":[13]},{"code":231,"indent":0,"parameters":[99,"SCP_Foundation_Logo",1,1,11,12,100,100,0,0]},{"code":234,"indent":0,"parameters":[99,[0,0,0,255],1,false]},{"code":232,"indent":0,"parameters":[99,0,1,1,11,12,100,100,255,0,20,true,0]},{"code":111,"indent":0,"parameters":[0,86,0]},{"code":122,"indent":1,"parameters":[6,6,0,4,"\"甚至成了更加堅實的盟友，因為大家都明白最大的敵人是誰。\""]},{"code":0,"indent":1,"parameters":[]},{"code":411,"indent":0,"parameters":[]},{"code":122,"indent":1,"parameters":[6,6,0,4,"\"基金會仍能與蛇之手在某種程度上合作，這使得GOC十分不滿。\""]},{"code":0,"indent":1,"parameters":[]},{"code":412,"indent":0,"parameters":[]},{"code":250,"indent":0,"parameters":[{"name":"Book1","volume":90,"pitch":100,"pan":0}]},{"code":111,"indent":0,"parameters":[0,51,1]},{"code":101,"indent":1,"parameters":["",0,1,2,""]},{"code":401,"indent":1,"parameters":["由於蛇之手盡可能沒有與基金會撕破臉，在歐提克之戰後，"]},{"code":401,"indent":1,"parameters":["\\v[6]"]},{"code":0,"indent":1,"parameters":[]},{"code":411,"indent":0,"parameters":[]},{"code":101,"indent":1,"parameters":["",0,1,2,""]},{"code":401,"indent":1,"parameters":["蛇之手與基金會撕破臉的後果就是在歐提克之戰後，"]},{"code":401,"indent":1,"parameters":["他們最痛恨的獄卒與焚書人成為了堅定的盟友，再次給他們帶來惡夢。"]},{"code":0,"indent":1,"parameters":[]},{"code":412,"indent":0,"parameters":[]},{"code":205,"indent":0,"parameters":[2,{"list":[{"code":39,"indent":null},{"code":0}],"repeat":false,"skippable":false,"wait":true}]},{"code":505,"indent":0,"parameters":[{"code":39,"indent":null}]},{"code":108,"indent":0,"parameters":["※敗者首領的狀況"]},{"code":122,"indent":0,"parameters":[53,53,0,0,8]},{"code":122,"indent":0,"parameters":[11,11,0,0,0]},{"code":122,"indent":0,"parameters":[12,12,0,0,0]},{"code":117,"indent":0,"parameters":[13]},{"code":231,"indent":0,"parameters":[99,"ending/Ending8_GFB",1,1,11,12,100,100,0,0]},{"code":234,"indent":0,"parameters":[99,[0,0,0,255],1,false]},{"code":232,"indent":0,"parameters":[99,0,1,1,11,12,100,100,255,0,20,true,0]},{"code":250,"indent":0,"parameters":[{"name":"Book1","volume":90,"pitch":100,"pan":0}]},{"code":101,"indent":0,"parameters":["14.GFB",0,1,2,""]},{"code":401,"indent":0,"parameters":["緁爾汀‧法蘭希斯‧布徹：G.F.B.、人間之神、頂級的現實扭曲者、蛇巢領導、屠夫、"]},{"code":401,"indent":0,"parameters":["瑪莉蘇中的瑪莉蘇、聯盟紅色警戒人物、歐提克之戰的主要策劃人、她有很多別號，"]},{"code":401,"indent":0,"parameters":["很多都很響亮，但都無法改變她這場戰爭中失敗的事實。"]},{"code":250,"indent":0,"parameters":[{"name":"Book1","volume":90,"pitch":100,"pan":0}]},{"code":101,"indent":0,"parameters":["14.GFB",0,1,2,""]},{"code":401,"indent":0,"parameters":["儘管一人就擁有足以毀滅星球的力量，但戰爭始終不是一個人就能打的，"]},{"code":401,"indent":0,"parameters":["終究身為現實扭曲者的她還是過於相信自身的力量導致落敗。"]},{"code":250,"indent":0,"parameters":[{"name":"Book1","volume":90,"pitch":100,"pan":0}]},{"code":101,"indent":0,"parameters":["14.GFB",0,1,2,""]},{"code":401,"indent":0,"parameters":["在多次與GOC的交鋒落敗後，聯盟觀測到，布徹做了下列行為："]},{"code":401,"indent":0,"parameters":["她憑藉一己之力打造了一艘宇宙戰艦、帶著她的追隨者們與大量超人類飛往了其他星系。"]},{"code":250,"indent":0,"parameters":[{"name":"Book1","volume":90,"pitch":100,"pan":0}]},{"code":101,"indent":0,"parameters":["14.GFB",5,1,2,""]},{"code":401,"indent":0,"parameters":["不久後，一顆疑似適合人類居住的行星被聯盟的超天文學家所發現，"]},{"code":401,"indent":0,"parameters":["儘管過往他們從未發現到這顆星球，甚至有人懷疑那顆星球在過往並不存在。"]},{"code":111,"indent":0,"parameters":[0,86,0]},{"code":108,"indent":1,"parameters":["※如果殺死奈爾或主角團，布徹會玩隕石丟丟樂"]},{"code":122,"indent":1,"parameters":[6,6,0,0,0]},{"code":111,"indent":1,"parameters":[0,85,0]},{"code":122,"indent":2,"parameters":[6,6,1,0,1]},{"code":0,"indent":2,"parameters":[]},{"code":412,"indent":1,"parameters":[]},{"code":111,"indent":1,"parameters":[0,39,0]},{"code":122,"indent":2,"parameters":[6,6,1,0,1]},{"code":0,"indent":2,"parameters":[]},{"code":412,"indent":1,"parameters":[]},{"code":111,"indent":1,"parameters":[1,6,0,1,1]},{"code":250,"indent":2,"parameters":[{"name":"Book1","volume":90,"pitch":100,"pan":0}]},{"code":101,"indent":2,"parameters":["14.GFB",2,1,2,""]},{"code":401,"indent":2,"parameters":["至今，該星系時不時都朝地球飛來足以毀滅地表所有生物的大型隕石，"]},{"code":401,"indent":2,"parameters":["成為了聯盟巨大麻煩之一，每一次都是人類可能滅亡的危機，"]},{"code":401,"indent":2,"parameters":["而這些現象實在很難不讓人與這位消失在地球上的蛇巢領導聯想在一起。"]},{"code":0,"indent":2,"parameters":[]},{"code":412,"indent":1,"parameters":[]},{"code":250,"indent":1,"parameters":[{"name":"Book1","volume":90,"pitch":100,"pan":0}]},{"code":101,"indent":1,"parameters":["14.GFB",0,1,2,""]},{"code":401,"indent":1,"parameters":["GOC目前沒有能到達至該星系的宇航技術，"]},{"code":401,"indent":1,"parameters":["面對可能的這個威脅GOC托勒密部門仍在加速開發相關載具。"]},{"code":0,"indent":1,"parameters":[]},{"code":411,"indent":0,"parameters":[]},{"code":101,"indent":1,"parameters":["14.GFB",0,1,2,""]},{"code":401,"indent":1,"parameters":["GOC內部評估認為她已不具立即的威脅性，"]},{"code":401,"indent":1,"parameters":["將超人類追隨者進行太空殖民反而幫了他們大忙，GOC也沒有對他們趕盡殺絕的必要。"]},{"code":0,"indent":1,"parameters":[]},{"code":412,"indent":0,"parameters":[]},{"code":108,"indent":0,"parameters":["※克拉倫斯的場合"]},{"code":231,"indent":0,"parameters":[99,"Actor4_Clarence_menu",0,0,690,140,100,100,0,0]},{"code":232,"indent":0,"parameters":[99,0,0,0,590,140,100,100,255,0,30,false,0]},{"code":250,"indent":0,"parameters":[{"name":"Book1","volume":90,"pitch":100,"pan":0}]},{"code":111,"indent":0,"parameters":[0,89,0]},{"code":122,"indent":1,"parameters":[6,6,0,4,"\"為了自己的正義，他最終殺死了過往自己尊敬的人。\""]},{"code":0,"indent":1,"parameters":[]},{"code":411,"indent":0,"parameters":[]},{"code":122,"indent":1,"parameters":[6,6,0,4,"他意識到自己再也無法待在聯盟之中。\""]},{"code":0,"indent":1,"parameters":[]},{"code":412,"indent":0,"parameters":[]},{"code":101,"indent":0,"parameters":["",0,1,2,""]},{"code":401,"indent":0,"parameters":["\\n[4]‧斐爾多‧羅賓遜，一個善於料理的英倫紳士，一個對正義有堅定信念的戰士，"]},{"code":401,"indent":0,"parameters":["\\v[6]"]},{"code":250,"indent":0,"parameters":[{"name":"Book1","volume":90,"pitch":100,"pan":0}]},{"code":111,"indent":0,"parameters":[1,32,0,26,1]},{"code":122,"indent":1,"parameters":[6,6,0,4,"\"在他與蛇之手合作救出SRA製造所裡的無辜綠型後，\""]},{"code":0,"indent":1,"parameters":[]},{"code":411,"indent":0,"parameters":[]},{"code":122,"indent":1,"parameters":[6,6,0,4,"\"多年與異常交戰與在他身上發生的事情讓他的心靈千瘡百孔，\""]},{"code":0,"indent":1,"parameters":[]},{"code":412,"indent":0,"parameters":[]},{"code":101,"indent":0,"parameters":["",0,1,2,""]},{"code":401,"indent":0,"parameters":["\\v[6]"]},{"code":401,"indent":0,"parameters":["聯盟已經沒有他的容身之地，最終他還是選擇退役了。"]},{"code":108,"indent":0,"parameters":["※瑪納的結局"]},{"code":408,"indent":0,"parameters":["完成隱藏任務「不可能的合作」 （２６）"]},{"code":408,"indent":0,"parameters":["在心理醫生支線任務時選擇：「克拉倫斯尋求更好的辦法」"]},{"code":408,"indent":0,"parameters":["沒有殺死泰勒。"]},{"code":122,"indent":0,"parameters":[6,6,0,0,0]},{"code":250,"indent":0,"parameters":[{"name":"Book1","volume":90,"pitch":100,"pan":0}]},{"code":111,"indent":0,"parameters":[1,32,0,26,1]},{"code":122,"indent":1,"parameters":[6,6,1,0,1]},{"code":0,"indent":1,"parameters":[]},{"code":412,"indent":0,"parameters":[]},{"code":111,"indent":0,"parameters":[0,89,1]},{"code":122,"indent":1,"parameters":[6,6,1,0,1]},{"code":0,"indent":1,"parameters":[]},{"code":412,"indent":0,"parameters":[]},{"code":111,"indent":0,"parameters":[8,35]},{"code":122,"indent":1,"parameters":[6,6,1,0,1]},{"code":0,"indent":1,"parameters":[]},{"code":412,"indent":0,"parameters":[]},{"code":108,"indent":0,"parameters":["※為3時代表加入瑪鈉"]},{"code":111,"indent":0,"parameters":[1,6,0,3,0]},{"code":101,"indent":1,"parameters":["12.others3",4,1,2,""]},{"code":401,"indent":1,"parameters":["在\\c[29]瑪納\\c[0]成員阿布薩彼特的引薦下，\\n[4]在退役後加入了瑪納慈善基金會，"]},{"code":401,"indent":1,"parameters":["過往他持槍與異常作戰，現在他以異常幫助能幫助的人們。"]},{"code":250,"indent":1,"parameters":[{"name":"Book1","volume":90,"pitch":100,"pan":0}]},{"code":101,"indent":1,"parameters":["",4,1,2,""]},{"code":401,"indent":1,"parameters":["儘管對那個恐怖的聖誕老人大仇未報，時而還是會從噩夢中驚醒，"]},{"code":401,"indent":1,"parameters":["但他曉得，過往身為士兵的他已經死了，似乎這才是他應該待在的位置上。"]},{"code":108,"indent":1,"parameters":["※由於瑪納是最優先結局，於是如果達成瑪納條件，將跳至"]},{"code":408,"indent":1,"parameters":["Actor4endflag此一標籤。"]},{"code":119,"indent":1,"parameters":["Actor4endflag"]},{"code":0,"indent":1,"parameters":[]},{"code":412,"indent":0,"parameters":[]},{"code":108,"indent":0,"parameters":["※基金會結局的場合"]},{"code":408,"indent":0,"parameters":["條件："]},{"code":408,"indent":0,"parameters":["在心理醫生支線任務通過（６），不論有沒有選擇追求細膩的作法"]},{"code":408,"indent":0,"parameters":["完成隱藏任務「謝禮」 （３）"]},{"code":122,"indent":0,"parameters":[6,6,0,0,0]},{"code":111,"indent":0,"parameters":[1,19,0,6,1]},{"code":122,"indent":1,"parameters":[6,6,1,0,1]},{"code":0,"indent":1,"parameters":[]},{"code":412,"indent":0,"parameters":[]},{"code":111,"indent":0,"parameters":[1,42,0,3,1]},{"code":122,"indent":1,"parameters":[6,6,1,0,1]},{"code":0,"indent":1,"parameters":[]},{"code":412,"indent":0,"parameters":[]},{"code":108,"indent":0,"parameters":["※為2時代表加入SCP基金會"]},{"code":111,"indent":0,"parameters":[1,6,0,2,0]},{"code":101,"indent":1,"parameters":["30.other8",1,1,2,""]},{"code":401,"indent":1,"parameters":["\\c[6]基金會\\c[0]在很早以前就注意到了\\n[4]這號人物存在，"]},{"code":401,"indent":1,"parameters":["他破壞SRA製造所的事情不只震動了GOC，也震動了基金會的高層，"]},{"code":401,"indent":1,"parameters":["在退役後他被吸納成為了SCP基金會的一員，曾被他救了一命的艾絲特‧布萊特對他的到來"]},{"code":401,"indent":1,"parameters":["表示歡迎。"]},{"code":250,"indent":1,"parameters":[{"name":"Book1","volume":90,"pitch":100,"pan":0}]},{"code":101,"indent":1,"parameters":["30.other8",0,1,2,""]},{"code":401,"indent":1,"parameters":["這位與他妹妹同名的女性成為了他的朋友，給予他很大的支持，"]},{"code":401,"indent":1,"parameters":["儘管時而他仍會因過往的創傷從噩夢中驚醒，"]},{"code":401,"indent":1,"parameters":["但在這位新朋友的支持下他的狀況的確顯著地在改善。"]},{"code":121,"indent":1,"parameters":[93,93,0]},{"code":108,"indent":1,"parameters":["※跳至Actor4endflag此一標籤。"]},{"code":119,"indent":1,"parameters":["Actor4endflag"]},{"code":0,"indent":1,"parameters":[]},{"code":412,"indent":0,"parameters":[]},{"code":108,"indent":0,"parameters":["※蛇之手結局的場合"]},{"code":408,"indent":0,"parameters":["知道錨的真相　（道具獲得）"]},{"code":408,"indent":0,"parameters":["通關心理醫生任務（６）（必定）"]},{"code":408,"indent":0,"parameters":["但沒選擇：「克拉倫斯尋求更好的辦法」"]},{"code":408,"indent":0,"parameters":["沒完成隱藏任務「謝禮」 （３）"]},{"code":408,"indent":0,"parameters":["如果有殺死泰勒的話再＋１"]},{"code":122,"indent":0,"parameters":[6,6,0,0,0]},{"code":111,"indent":0,"parameters":[8,35]},{"code":0,"indent":1,"parameters":[]},{"code":411,"indent":0,"parameters":[]},{"code":122,"indent":1,"parameters":[6,6,1,0,1]},{"code":0,"indent":1,"parameters":[]},{"code":412,"indent":0,"parameters":[]},{"code":111,"indent":0,"parameters":[8,44]},{"code":122,"indent":1,"parameters":[6,6,1,0,1]},{"code":0,"indent":1,"parameters":[]},{"code":412,"indent":0,"parameters":[]},{"code":111,"indent":0,"parameters":[0,89,0]},{"code":122,"indent":1,"parameters":[6,6,1,0,1]},{"code":0,"indent":1,"parameters":[]},{"code":412,"indent":0,"parameters":[]},{"code":108,"indent":0,"parameters":["※看心理醫生是必要條件，"]},{"code":408,"indent":0,"parameters":["玩家要通過心理醫生任務才知道他的心理創傷"]},{"code":111,"indent":0,"parameters":[1,19,0,6,1]},{"code":122,"indent":1,"parameters":[6,6,1,0,1]},{"code":0,"indent":1,"parameters":[]},{"code":411,"indent":0,"parameters":[]},{"code":122,"indent":1,"parameters":[6,6,0,0,0]},{"code":0,"indent":1,"parameters":[]},{"code":412,"indent":0,"parameters":[]},{"code":108,"indent":0,"parameters":["※這個條件比較特殊只要有３以上就算達成"]},{"code":111,"indent":0,"parameters":[1,6,0,3,0]},{"code":101,"indent":1,"parameters":["",1,1,2,""]},{"code":401,"indent":1,"parameters":["在正義感與復仇心驅使下，\\n[4]在歐提克之戰加入了蛇之手，"]},{"code":401,"indent":1,"parameters":["他一開始覺得這是好的選擇，即便曾為焚書人的他也被\\c[3]圖書館\\c[0]所接納。"]},{"code":250,"indent":1,"parameters":[{"name":"Book1","volume":90,"pitch":100,"pan":0}]},{"code":101,"indent":1,"parameters":["",0,1,2,""]},{"code":401,"indent":1,"parameters":["在圖書館裡獲取異常知識的他某一天有了自信心，"]},{"code":401,"indent":1,"parameters":["決心去找當初殺害他家人的恐怖聖誕老人復仇，他帶了所有能帶的武器與裝備，"]},{"code":401,"indent":1,"parameters":["準備各式各樣的異常物品與魔法去進行他一個人的戰爭，然後再也沒有回來。"]},{"code":108,"indent":1,"parameters":["※跳至Actor4endflag此一標籤，這是為了跳過酒鬼結局的顯示。"]},{"code":119,"indent":1,"parameters":["Actor4endflag"]},{"code":0,"indent":1,"parameters":[]},{"code":412,"indent":0,"parameters":[]},{"code":108,"indent":0,"parameters":["※克拉倫斯結局的結尾，如果所有上述條件克拉倫斯都沒有達成，"]},{"code":408,"indent":0,"parameters":["他將成為酒鬼每日泡在酒中，也放棄了自身的料理，"]},{"code":408,"indent":0,"parameters":["並且某一天被人發現在個人公寓中飲彈自盡。"]},{"code":108,"indent":0,"parameters":["※酒鬼加自殺的最悲慘結局之場合。"]},{"code":101,"indent":0,"parameters":["",1,1,2,""]},{"code":401,"indent":0,"parameters":["\\n[4]在退役後沒能找到新的棲身之所，"]},{"code":401,"indent":0,"parameters":["內心滿是創傷的他成了一個終日活在酒瓶之間的醉鬼，不但放下了槍，"]},{"code":401,"indent":0,"parameters":["連過往很得意的料理也被他放棄了。"]},{"code":250,"indent":0,"parameters":[{"name":"Book1","volume":90,"pitch":100,"pan":0}]},{"code":101,"indent":0,"parameters":["",1,1,2,""]},{"code":401,"indent":0,"parameters":["某一日，\\n[4]個人公寓裡傳來了一聲槍響，"]},{"code":401,"indent":0,"parameters":["鄰居發現他時，他已然飲彈自盡。"]},{"code":108,"indent":0,"parameters":["※Actor4endflag"]},{"code":408,"indent":0,"parameters":["這個標籤是為了跳過最悽慘的酒鬼結局"]},{"code":118,"indent":0,"parameters":["Actor4endflag"]},{"code":108,"indent":0,"parameters":["※消除圖片"]},{"code":232,"indent":0,"parameters":[99,0,0,0,690,140,100,100,0,0,30,true,0]},{"code":108,"indent":0,"parameters":["※埃瓦里斯的場合"]},{"code":231,"indent":0,"parameters":[99,"Actor3_Evariste_menu",0,0,390,240,100,100,0,0]},{"code":232,"indent":0,"parameters":[99,0,0,0,420,240,100,100,255,0,30,false,0]},{"code":250,"indent":0,"parameters":[{"name":"Book1","volume":90,"pitch":100,"pan":0}]},{"code":101,"indent":0,"parameters":["",3,1,2,""]},{"code":401,"indent":0,"parameters":["\\n[3]‧勒菲弗爾，這位來自法國的光明會成員，一直以來都充滿著活力與理想，"]},{"code":401,"indent":0,"parameters":["儘管在這這些戰事後，他已經不曉得過往能否如此單純地看待這灰色的世界。"]},{"code":250,"indent":0,"parameters":[{"name":"Book1","volume":90,"pitch":100,"pan":0}]},{"code":101,"indent":0,"parameters":["",3,1,2,""]},{"code":401,"indent":0,"parameters":["他才明白這或許也巴伐利亞光明會成立的原因："]},{"code":401,"indent":0,"parameters":["為了讓這灰色的世界變得更少一些黑暗一些。"]},{"code":108,"indent":0,"parameters":["※三波特蘭紅翼行動相關事件"]},{"code":250,"indent":0,"parameters":[{"name":"Book1","volume":90,"pitch":100,"pan":0}]},{"code":111,"indent":0,"parameters":[0,67,0]},{"code":101,"indent":1,"parameters":["",3,1,2,""]},{"code":401,"indent":1,"parameters":["在原隊長三波特蘭殺死平民與孩童的作為讓他始終耿耿於懷，"]},{"code":401,"indent":1,"parameters":["不久後就與林肯決裂，他永不可能與下令殺死無辜平民的領導者成為朋友。"]},{"code":0,"indent":1,"parameters":[]},{"code":411,"indent":0,"parameters":[]},{"code":101,"indent":1,"parameters":["",3,1,2,""]},{"code":401,"indent":1,"parameters":["三波特蘭之戰的事情讓他仍暗暗自責，但即便最終沒能救下那一家子人，"]},{"code":401,"indent":1,"parameters":["\\n[1]‧林肯也已經永久獲得他的尊敬了，兩人成為了好朋友。"]},{"code":108,"indent":1,"parameters":["※如果林肯會被做成錨，"]},{"code":408,"indent":1,"parameters":["林肯將會失蹤而埃瓦里斯嘗試找他"]},{"code":111,"indent":1,"parameters":[0,90,0]},{"code":101,"indent":2,"parameters":["",3,1,2,""]},{"code":401,"indent":2,"parameters":["只不過．後來林肯失蹤的消息令他十分擔憂，"]},{"code":401,"indent":2,"parameters":["儘管直到他的餘生他都沒能找到這位好友林肯的所在地。"]},{"code":0,"indent":2,"parameters":[]},{"code":412,"indent":1,"parameters":[]},{"code":0,"indent":1,"parameters":[]},{"code":412,"indent":0,"parameters":[]},{"code":108,"indent":0,"parameters":["※結局一：與奧蕾絲生活的條件："]},{"code":408,"indent":0,"parameters":["擁有奧蕾絲的戀心，且是非殺戮結局"]},{"code":408,"indent":0,"parameters":["此為最優先結局。"]},{"code":111,"indent":0,"parameters":[8,47]},{"code":250,"indent":1,"parameters":[{"name":"Book1","volume":90,"pitch":100,"pan":0}]},{"code":111,"indent":1,"parameters":[0,85,0]},{"code":101,"indent":2,"parameters":["10.Orlaith",2,1,2,""]},{"code":401,"indent":2,"parameters":["儘管\\n[11]與\\n[3]成為了戀人，但\\n[11]不可能原諒殺死她朋友們的人，"]},{"code":401,"indent":2,"parameters":["本打算戰後就一同生活隱居的兩人如今變回了敵人。"]},{"code":0,"indent":2,"parameters":[]},{"code":411,"indent":1,"parameters":[]},{"code":101,"indent":2,"parameters":["10.Orlaith",7,1,2,""]},{"code":401,"indent":2,"parameters":["\\n[3]決定離開GOC，並與\\n[11]一同生活，"]},{"code":401,"indent":2,"parameters":["這位希神女性也放下自己蛇之手的事業，將蛇之手與GOC之間的鬥爭拋諸腦後一同生活。"]},{"code":111,"indent":2,"parameters":[0,86,0]},{"code":250,"indent":3,"parameters":[{"name":"Book1","volume":90,"pitch":100,"pan":0}]},{"code":101,"indent":3,"parameters":["10.Orlaith",6,1,2,""]},{"code":401,"indent":3,"parameters":["但隨著GOC維持的舊世界狀況不斷的惡化，"]},{"code":401,"indent":3,"parameters":["\\n[11]出於責任感認為自己再也不能對當今世上發生的事視而不見。"]},{"code":250,"indent":3,"parameters":[{"name":"Book1","volume":90,"pitch":100,"pan":0}]},{"code":101,"indent":3,"parameters":["10.Orlaith",6,1,2,""]},{"code":401,"indent":3,"parameters":["某天她留下了一封信離開了\\n[3]，重新投入了蛇之手的事業中。"]},{"code":0,"indent":3,"parameters":[]},{"code":412,"indent":2,"parameters":[]},{"code":0,"indent":2,"parameters":[]},{"code":412,"indent":1,"parameters":[]},{"code":108,"indent":1,"parameters":["※跳轉到結尾行動標籤，避免成為戀人又成為朋友"]},{"code":119,"indent":1,"parameters":["Actor3endflag"]},{"code":0,"indent":1,"parameters":[]},{"code":412,"indent":0,"parameters":[]},{"code":108,"indent":0,"parameters":["※結局二：在新世界秩序上努力"]},{"code":408,"indent":0,"parameters":["讓奧蕾絲存活且經過約會但沒有戀心、戰爭結局會讓他感到沮喪"]},{"code":108,"indent":0,"parameters":["結局二：在新世界秩序上努力"]},{"code":408,"indent":0,"parameters":["條件為讓奧蕾絲存活但沒有與奧蕾絲發展成戀人。"]},{"code":111,"indent":0,"parameters":[1,22,0,15,1]},{"code":250,"indent":1,"parameters":[{"name":"Book1","volume":90,"pitch":100,"pan":0}]},{"code":101,"indent":1,"parameters":["",6,1,2,""]},{"code":401,"indent":1,"parameters":["不知是出於仁慈還是傲慢，"]},{"code":401,"indent":1,"parameters":["這位光明會的成員當初在歐提克放了蛇巢領導\\n[11]一馬，"]},{"code":401,"indent":1,"parameters":["當初兩人之間恐怕也沒想過一位GOC成員與蛇之手會成為朋友。"]},{"code":250,"indent":1,"parameters":[{"name":"Book1","volume":90,"pitch":100,"pan":0}]},{"code":101,"indent":1,"parameters":["",6,1,2,""]},{"code":401,"indent":1,"parameters":["不如許多外人謠傳的陰謀論那樣，"]},{"code":401,"indent":1,"parameters":["新世界秩序的目標其實是要提倡理性主義創造重視人權與削減迷信的新世界，"]},{"code":401,"indent":1,"parameters":["打造一個不論性別與宗教自由都能被平等對待的世界，這也是\\n[3]加入其中的原因。"]},{"code":111,"indent":1,"parameters":[0,86,0]},{"code":250,"indent":2,"parameters":[{"name":"Book1","volume":90,"pitch":100,"pan":0}]},{"code":101,"indent":2,"parameters":["",6,1,2,""]},{"code":401,"indent":2,"parameters":["然而，隨著GOC的影響力日漸增大，他們對整個異常世界的控制力也越來越強了，"]},{"code":401,"indent":2,"parameters":["偏見與狂熱越發越增長，光明會的理想似乎離現實越來越遠，"]},{"code":401,"indent":2,"parameters":["這也讓\\n[3]感到無比沮喪。"]},{"code":0,"indent":2,"parameters":[]},{"code":412,"indent":1,"parameters":[]},{"code":250,"indent":1,"parameters":[{"name":"Book1","volume":90,"pitch":100,"pan":0}]},{"code":108,"indent":1,"parameters":["※跳轉到紅翼行動標籤"]},{"code":119,"indent":1,"parameters":["Actor3endflag"]},{"code":0,"indent":1,"parameters":[]},{"code":412,"indent":0,"parameters":[]},{"code":118,"indent":0,"parameters":["Actor3endflag"]},{"code":108,"indent":0,"parameters":["※消除圖片"]},{"code":232,"indent":0,"parameters":[99,0,0,0,420,240,100,100,0,0,30,true,0]},{"code":108,"indent":0,"parameters":["※歐萊希雅的場合"]},{"code":231,"indent":0,"parameters":[99,"Actor2_Olesya_menu",0,0,400,170,100,100,0,0]},{"code":232,"indent":0,"parameters":[99,0,0,0,600,170,100,100,255,0,30,false,0]},{"code":108,"indent":0,"parameters":["※學者劇情的場合"]},{"code":122,"indent":0,"parameters":[6,6,0,0,0]},{"code":108,"indent":0,"parameters":["※計算學者值："]},{"code":408,"indent":0,"parameters":["欲肉教所有的知識都有拿到、並且有參加慈善晚會就會成為學者"]},{"code":111,"indent":0,"parameters":[1,23,0,4,1]},{"code":122,"indent":1,"parameters":[6,6,1,0,1]},{"code":0,"indent":1,"parameters":[]},{"code":412,"indent":0,"parameters":[]},{"code":122,"indent":0,"parameters":[6,6,1,3,0,27,0]},{"code":122,"indent":0,"parameters":[6,6,1,3,0,28,0]},{"code":111,"indent":0,"parameters":[1,6,0,3,1]},{"code":122,"indent":1,"parameters":[7,7,0,4,"\"在前線作戰的經驗讓她有機會接觸更多知識，不久後就轉往ICSUT作為一位專職的研究學者。\""]},{"code":0,"indent":1,"parameters":[]},{"code":411,"indent":0,"parameters":[]},{"code":122,"indent":1,"parameters":[7,7,0,4,"\"在前線作戰的經驗並沒有讓她受到太多影響，她忠實著執行後勤任務。\""]},{"code":0,"indent":1,"parameters":[]},{"code":412,"indent":0,"parameters":[]},{"code":101,"indent":0,"parameters":["",2,1,2,""]},{"code":401,"indent":0,"parameters":["在戰後不久\\n[10]小組就宣告解散，\\n[2]回到了托勒密部門工作，"]},{"code":401,"indent":0,"parameters":["\\V[7]"]},{"code":122,"indent":0,"parameters":[7,7,0,0,0]},{"code":108,"indent":0,"parameters":["※安東尼告白相關的部分"]},{"code":111,"indent":0,"parameters":[0,91,0]},{"code":250,"indent":1,"parameters":[{"name":"Book1","volume":90,"pitch":100,"pan":0}]},{"code":101,"indent":1,"parameters":["01.GOC1",2,1,2,""]},{"code":401,"indent":1,"parameters":["此外，\\n[1]還向\\n[2]提出作為情侶交往的請求，"]},{"code":401,"indent":1,"parameters":["\\n[1]似乎一直默默喜歡這個支持著他的新人。"]},{"code":250,"indent":1,"parameters":[{"name":"Book1","volume":90,"pitch":100,"pan":0}]},{"code":101,"indent":1,"parameters":["",5,1,2,""]},{"code":401,"indent":1,"parameters":["\\n[2]對戀愛一向毫無經驗與興趣，她倒不是對男人毫無想法，"]},{"code":401,"indent":1,"parameters":["但更吸引她的只有知識與貓咪，這也是某些同事認為她缺乏人性的理由，"]},{"code":401,"indent":1,"parameters":["\\n[1]竟對她抱持這樣的情感讓她感到十分的訝異。"]},{"code":111,"indent":1,"parameters":[0,92,0]},{"code":101,"indent":2,"parameters":["06.GOC3",6,1,2,""]},{"code":401,"indent":2,"parameters":["儘管如此，\\n[2]還是願意給\\n[1]一次機會，"]},{"code":401,"indent":2,"parameters":["成為情侶後的兩人變得十分恩愛，或許有點恩愛過頭，"]},{"code":401,"indent":2,"parameters":["照她所說：「我們都快變成傻瓜了」，令她有些害怕。"]},{"code":250,"indent":2,"parameters":[{"name":"Book1","volume":90,"pitch":100,"pan":0}]},{"code":101,"indent":2,"parameters":["01.GOC1",7,1,2,""]},{"code":401,"indent":2,"parameters":["不僅如此，和\\n[1]成為情侶後，也讓她發覺了\\n[1]似乎還有其他方面的特別天賦，"]},{"code":401,"indent":2,"parameters":["這不只是指\\n[1]的是位頗有才華的鋼琴愛好者，他還有別的些不太尋常的天賦，"]},{"code":401,"indent":2,"parameters":["她不曉得那些是他自身的天賦還是身為綠型的影響，"]},{"code":401,"indent":2,"parameters":["而身為學者抱持的探求慾望如今向\\n[1]投去。"]},{"code":250,"indent":2,"parameters":[{"name":"Book1","volume":90,"pitch":100,"pan":0}]},{"code":101,"indent":2,"parameters":["06.GOC3",6,1,2,""]},{"code":401,"indent":2,"parameters":["總體而言，兩人之間的關係幸福與融洽到了旁人要忌妒到不行的地步，"]},{"code":401,"indent":2,"parameters":["向朋友介紹\\n[1]時，她有時會如此說："]},{"code":401,"indent":2,"parameters":["「我男朋友各方面都很優秀喔，除了有時會變成變態禽獸。」"]},{"code":0,"indent":2,"parameters":[]},{"code":411,"indent":1,"parameters":[]},{"code":101,"indent":2,"parameters":["06.GOC3",7,1,2,""]},{"code":401,"indent":2,"parameters":["對戀愛毫無興趣的\\n[2]自然對\\n[1]也毫無興趣，"]},{"code":401,"indent":2,"parameters":["她並不是不理解為何有人希望彼此依靠，只是她更寧願在吸收知識與吸貓咪，"]},{"code":401,"indent":2,"parameters":["再說——\\n[1]本來就不是她的喜歡的型。"]},{"code":0,"indent":2,"parameters":[]},{"code":412,"indent":1,"parameters":[]},{"code":0,"indent":1,"parameters":[]},{"code":412,"indent":0,"parameters":[]},{"code":108,"indent":0,"parameters":["※移除圖片"]},{"code":232,"indent":0,"parameters":[99,0,0,0,400,170,100,100,0,0,30,true,0]},{"code":108,"indent":0,"parameters":["※安東尼的場合"]},{"code":231,"indent":0,"parameters":[99,"Actor1_Antony_menu",0,0,400,145,100,100,0,0]},{"code":232,"indent":0,"parameters":[99,0,0,0,490,145,100,100,255,0,30,false,0]},{"code":250,"indent":0,"parameters":[{"name":"Book1","volume":90,"pitch":100,"pan":0}]},{"code":101,"indent":0,"parameters":["",7,1,2,""]},{"code":401,"indent":0,"parameters":["在歐提克之戰後，秩序維護者們成功維護了和平，"]},{"code":401,"indent":0,"parameters":["而這位\\n[10]小組的隊長\\n[1]迎來了他的結局。"]},{"code":250,"indent":0,"parameters":[{"name":"Book1","volume":90,"pitch":100,"pan":0}]},{"code":111,"indent":0,"parameters":[0,90,0]},{"code":108,"indent":1,"parameters":["成為錨的結局"]},{"code":101,"indent":1,"parameters":["",7,1,2,""]},{"code":401,"indent":1,"parameters":["儘管議長D.C. Al Fine警告過\\n[1]必須對自己的身份保密一事，"]},{"code":401,"indent":1,"parameters":["但\\n[1]‧林肯對似乎沒有把這個警告放在心上。"]},{"code":250,"indent":1,"parameters":[{"name":"Book1","volume":90,"pitch":100,"pan":0}]},{"code":101,"indent":1,"parameters":["",7,1,2,""]},{"code":401,"indent":1,"parameters":["在\\n[10]解散不久後，在泰勒總指揮官的默許下，\\n[1]開始他的逃亡生活，"]},{"code":401,"indent":1,"parameters":["但——這個世界現在是GOC所掌握的，他又能逃到哪裡去呢？"]},{"code":122,"indent":1,"parameters":[53,53,0,0,10]},{"code":108,"indent":1,"parameters":["※傳送到指定位置"]},{"code":250,"indent":1,"parameters":[{"name":"Book1","volume":90,"pitch":100,"pan":0}]},{"code":232,"indent":1,"parameters":[99,0,0,0,400,145,100,100,0,0,30,true,0]},{"code":221,"indent":1,"parameters":[]},{"code":117,"indent":1,"parameters":[6]},{"code":129,"indent":1,"parameters":[17,0,true]},{"code":313,"indent":1,"parameters":[0,17,0,47]},{"code":111,"indent":1,"parameters":[0,39,1]},{"code":129,"indent":2,"parameters":[12,0,false]},{"code":0,"indent":2,"parameters":[]},{"code":412,"indent":1,"parameters":[]},{"code":314,"indent":1,"parameters":[0,0]},{"code":108,"indent":1,"parameters":["※傳送到指定位置"]},{"code":408,"indent":1,"parameters":["把所有臨時變數歸零"]},{"code":122,"indent":1,"parameters":[6,10,0,0,0]},{"code":201,"indent":1,"parameters":[0,176,25,29,8,2]},{"code":115,"indent":1,"parameters":[]},{"code":0,"indent":1,"parameters":[]},{"code":411,"indent":0,"parameters":[]},{"code":108,"indent":1,"parameters":["※林肯成為新的總指揮官的條件，沒有復仇"]},{"code":111,"indent":1,"parameters":[1,38,0,1,1]},{"code":108,"indent":2,"parameters":["※普通結局"]},{"code":101,"indent":2,"parameters":["",7,1,2,""]},{"code":401,"indent":2,"parameters":["儘管議長D.C. Al Fine大力推舉，\\n[1]最終還是沒有成為歐提克物的總指揮官，"]},{"code":401,"indent":2,"parameters":["在他與米茲蠟希的關係被拿出來討論後，"]},{"code":401,"indent":2,"parameters":["他毫不猶豫公報私仇的作為被認為太過衝動而不適合擔當高位。"]},{"code":250,"indent":2,"parameters":[{"name":"Book1","volume":90,"pitch":100,"pan":0}]},{"code":101,"indent":2,"parameters":["",7,1,2,""]},{"code":401,"indent":2,"parameters":["事後D.C. Al Fine也認為拿這點誘惑他是個失算，"]},{"code":401,"indent":2,"parameters":["但即使如此仍未損及他作為聯盟英雄的名聲太多，"]},{"code":401,"indent":2,"parameters":["直到退役前\\n[1]‧林肯這位聯盟成員仍在位聯盟立下各種赫赫戰功。"]},{"code":250,"indent":2,"parameters":[{"name":"Book1","volume":90,"pitch":100,"pan":0}]},{"code":232,"indent":2,"parameters":[99,0,0,0,400,145,100,100,0,0,30,true,0]},{"code":221,"indent":2,"parameters":[]},{"code":223,"indent":2,"parameters":[[0,0,0,0],1,false]},{"code":201,"indent":2,"parameters":[0,167,8,6,0,0]},{"code":222,"indent":2,"parameters":[]},{"code":115,"indent":2,"parameters":[]},{"code":0,"indent":2,"parameters":[]},{"code":411,"indent":1,"parameters":[]},{"code":108,"indent":2,"parameters":["※特殊結局"]},{"code":122,"indent":2,"parameters":[53,53,0,0,10]},{"code":101,"indent":2,"parameters":["",7,1,2,""]},{"code":401,"indent":2,"parameters":["在D.C. Al Fine大力推舉下，在歐提克之戰兩年後，"]},{"code":401,"indent":2,"parameters":["\\n[1]成為了歷任最年輕的歐提克總指揮官。"]},{"code":250,"indent":2,"parameters":[{"name":"Book1","volume":90,"pitch":100,"pan":0}]},{"code":232,"indent":2,"parameters":[99,0,0,0,400,145,100,100,0,0,30,true,0]},{"code":221,"indent":2,"parameters":[]},{"code":108,"indent":2,"parameters":["※傳送到指定位置"]},{"code":223,"indent":2,"parameters":[[0,0,0,0],1,false]},{"code":117,"indent":2,"parameters":[6]},{"code":129,"indent":2,"parameters":[1,0,false]},{"code":205,"indent":2,"parameters":[-1,{"list":[{"code":16,"indent":null},{"code":38,"indent":null},{"code":40,"indent":null},{"code":0}],"repeat":false,"skippable":false,"wait":true}]},{"code":505,"indent":2,"parameters":[{"code":16,"indent":null}]},{"code":505,"indent":2,"parameters":[{"code":38,"indent":null}]},{"code":505,"indent":2,"parameters":[{"code":40,"indent":null}]},{"code":201,"indent":2,"parameters":[0,131,13,6,2,0]},{"code":115,"indent":2,"parameters":[]},{"code":0,"indent":2,"parameters":[]},{"code":412,"indent":1,"parameters":[]},{"code":115,"indent":1,"parameters":[]},{"code":0,"indent":1,"parameters":[]},{"code":412,"indent":0,"parameters":[]},{"code":0,"indent":0,"parameters":[]}],"moveFrequency":3,"moveRoute":{"list":[{"code":0,"parameters":[]}],"repeat":true,"skippable":false,"wait":false},"moveSpeed":3,"moveType":0,"priorityType":0,"stepAnime":false,"through":false,"trigger":3,"walkAnime":true}],"x":8,"y":4},
{"id":2,"name":"人物表演用","note":"","pages":[{"conditions":{"actorId":1,"actorValid":false,"itemId":1,"itemValid":false,"selfSwitchCh":"A","selfSwitchValid":false,"switch1Id":1,"switch1Valid":false,"switch2Id":1,"switch2Valid":false,"variableId":1,"variableValid":false,"variableValue":0},"directionFix":false,"image":{"tileId":0,"characterName":"4666","direction":2,"pattern":1,"characterIndex":1},"list":[{"code":108,"indent":0,"parameters":["需要解釋的內容"]},{"code":108,"indent":0,"parameters":["世界的狀況"]},{"code":408,"indent":0,"parameters":["歐提克的狀況"]},{"code":408,"indent":0,"parameters":["三波特蘭的狀況"]},{"code":408,"indent":0,"parameters":["伊瓦迪村的狀況"]},{"code":408,"indent":0,"parameters":["哈伯希爾的狀況"]},{"code":408,"indent":0,"parameters":["米茲蠟希(沒死的話)的狀況"]},{"code":108,"indent":0,"parameters":["基金會的狀況"]},{"code":408,"indent":0,"parameters":["敗者首領的詳細狀況"]},{"code":408,"indent":0,"parameters":["勝者首領的狀況（如果有必要）"]},{"code":408,"indent":0,"parameters":["四位角色的狀況"]},{"code":0,"indent":0,"parameters":[]}],"moveFrequency":3,"moveRoute":{"list":[{"code":0,"parameters":[]}],"repeat":true,"skippable":false,"wait":false},"moveSpeed":3,"moveType":0,"priorityType":1,"stepAnime":true,"through":false,"trigger":0,"walkAnime":true}],"x":8,"y":5}
]
}